{
  "a_comp_cor_00": {
    "CumulativeVarianceExplained": 0.0255443161,
    "Mask": "combined",
    "Method": "aCompCor",
    "Retained": true,
    "SingularValue": 120.5483552814,
    "VarianceExplained": 0.0255443161
  },
  "a_comp_cor_01": {
    "CumulativeVarianceExplained": 0.045592158,
    "Mask": "combined",
    "Method": "aCompCor",
    "Retained": true,
    "SingularValue": 106.7942731728,
    "VarianceExplained": 0.0200478419
  },
  "a_comp_cor_02": {
    "CumulativeVarianceExplained": 0.0619271634,
    "Mask": "combined",
    "Method": "aCompCor",
    "Retained": true,
    "SingularValue": 96.3992803994,
    "VarianceExplained": 0.0163350055
  },
  "a_comp_cor_03": {
    "CumulativeVarianceExplained": 0.077330289,
    "Mask": "combined",
    "Method": "aCompCor",
    "Retained": true,
    "SingularValue": 93.6092096048,
    "VarianceExplained": 0.0154031256
  },
  "a_comp_cor_04": {
    "CumulativeVarianceExplained": 0.0910054802,
    "Mask": "combined",
    "Method": "aCompCor",
    "Retained": true,
    "SingularValue": 88.2024913972,
    "VarianceExplained": 0.0136751911
  },
  "a_comp_cor_05": {
    "CumulativeVarianceExplained": 0.103145951,
    "Mask": "combined",
    "Method": "aCompCor",
    "Retained": true,
    "SingularValue": 83.1059111972,
    "VarianceExplained": 0.0121404709
  },
  "a_comp_cor_06": {
    "CumulativeVarianceExplained": 0.1147914977,
    "Mask": "combined",
    "Method": "aCompCor",
    "Retained": true,
    "SingularValue": 81.3943180197,
    "VarianceExplained": 0.0116455466
  },
  "a_comp_cor_07": {
    "CumulativeVarianceExplained": 0.1244509218,
    "Mask": "combined",
    "Method": "aCompCor",
    "Retained": true,
    "SingularValue": 74.1292775927,
    "VarianceExplained": 0.0096594241
  },
  "a_comp_cor_08": {
    "CumulativeVarianceExplained": 0.1336622389,
    "Mask": "combined",
    "Method": "aCompCor",
    "Retained": true,
    "SingularValue": 72.3894065471,
    "VarianceExplained": 0.0092113171
  },
  "a_comp_cor_09": {
    "CumulativeVarianceExplained": 0.1424304083,
    "Mask": "combined",
    "Method": "aCompCor",
    "Retained": true,
    "SingularValue": 70.6266516983,
    "VarianceExplained": 0.0087681695
  },
  "a_comp_cor_10": {
    "CumulativeVarianceExplained": 0.1507345686,
    "Mask": "combined",
    "Method": "aCompCor",
    "Retained": true,
    "SingularValue": 68.73247948,
    "VarianceExplained": 0.0083041603
  },
  "a_comp_cor_11": {
    "CumulativeVarianceExplained": 0.1588072494,
    "Mask": "combined",
    "Method": "aCompCor",
    "Retained": true,
    "SingularValue": 67.7677459419,
    "VarianceExplained": 0.0080726808
  },
  "a_comp_cor_12": {
    "CumulativeVarianceExplained": 0.1664833486,
    "Mask": "combined",
    "Method": "aCompCor",
    "Retained": true,
    "SingularValue": 66.0821915825,
    "VarianceExplained": 0.0076760991
  },
  "a_comp_cor_13": {
    "CumulativeVarianceExplained": 0.1740639343,
    "Mask": "combined",
    "Method": "aCompCor",
    "Retained": true,
    "SingularValue": 65.6697752523,
    "VarianceExplained": 0.0075805857
  },
  "a_comp_cor_14": {
    "CumulativeVarianceExplained": 0.1814768123,
    "Mask": "combined",
    "Method": "aCompCor",
    "Retained": true,
    "SingularValue": 64.9392962018,
    "VarianceExplained": 0.007412878
  },
  "a_comp_cor_15": {
    "CumulativeVarianceExplained": 0.1887585455,
    "Mask": "combined",
    "Method": "aCompCor",
    "Retained": true,
    "SingularValue": 64.3622963622,
    "VarianceExplained": 0.0072817332
  },
  "a_comp_cor_16": {
    "CumulativeVarianceExplained": 0.1958350334,
    "Mask": "combined",
    "Method": "aCompCor",
    "Retained": true,
    "SingularValue": 63.4487448281,
    "VarianceExplained": 0.0070764879
  },
  "a_comp_cor_17": {
    "CumulativeVarianceExplained": 0.202589567,
    "Mask": "combined",
    "Method": "aCompCor",
    "Retained": true,
    "SingularValue": 61.9886004847,
    "VarianceExplained": 0.0067545335
  },
  "a_comp_cor_18": {
    "CumulativeVarianceExplained": 0.2092297439,
    "Mask": "combined",
    "Method": "aCompCor",
    "Retained": true,
    "SingularValue": 61.4616160652,
    "VarianceExplained": 0.0066401769
  },
  "a_comp_cor_19": {
    "CumulativeVarianceExplained": 0.2156642446,
    "Mask": "combined",
    "Method": "aCompCor",
    "Retained": true,
    "SingularValue": 60.5022568681,
    "VarianceExplained": 0.0064345007
  },
  "a_comp_cor_20": {
    "CumulativeVarianceExplained": 0.2220720138,
    "Mask": "combined",
    "Method": "aCompCor",
    "Retained": true,
    "SingularValue": 60.3764510863,
    "VarianceExplained": 0.0064077692
  },
  "a_comp_cor_21": {
    "CumulativeVarianceExplained": 0.2283519893,
    "Mask": "combined",
    "Method": "aCompCor",
    "Retained": true,
    "SingularValue": 59.7713582734,
    "VarianceExplained": 0.0062799755
  },
  "a_comp_cor_22": {
    "CumulativeVarianceExplained": 0.2345852723,
    "Mask": "combined",
    "Method": "aCompCor",
    "Retained": true,
    "SingularValue": 59.5487394267,
    "VarianceExplained": 0.006233283
  },
  "a_comp_cor_23": {
    "CumulativeVarianceExplained": 0.2407321948,
    "Mask": "combined",
    "Method": "aCompCor",
    "Retained": true,
    "SingularValue": 59.1347846399,
    "VarianceExplained": 0.0061469225
  },
  "a_comp_cor_24": {
    "CumulativeVarianceExplained": 0.2468024755,
    "Mask": "combined",
    "Method": "aCompCor",
    "Retained": true,
    "SingularValue": 58.7649722303,
    "VarianceExplained": 0.0060702807
  },
  "a_comp_cor_25": {
    "CumulativeVarianceExplained": 0.2528506143,
    "Mask": "combined",
    "Method": "aCompCor",
    "Retained": true,
    "SingularValue": 58.6576994045,
    "VarianceExplained": 0.0060481388
  },
  "a_comp_cor_26": {
    "CumulativeVarianceExplained": 0.2588257167,
    "Mask": "combined",
    "Method": "aCompCor",
    "Retained": true,
    "SingularValue": 58.302452831,
    "VarianceExplained": 0.0059751024
  },
  "a_comp_cor_27": {
    "CumulativeVarianceExplained": 0.264747099,
    "Mask": "combined",
    "Method": "aCompCor",
    "Retained": true,
    "SingularValue": 58.0397723344,
    "VarianceExplained": 0.0059213823
  },
  "a_comp_cor_28": {
    "CumulativeVarianceExplained": 0.2706063674,
    "Mask": "combined",
    "Method": "aCompCor",
    "Retained": true,
    "SingularValue": 57.7345578725,
    "VarianceExplained": 0.0058592684
  },
  "a_comp_cor_29": {
    "CumulativeVarianceExplained": 0.276399472,
    "Mask": "combined",
    "Method": "aCompCor",
    "Retained": true,
    "SingularValue": 57.4076588618,
    "VarianceExplained": 0.0057931046
  },
  "a_comp_cor_30": {
    "CumulativeVarianceExplained": 0.2821639912,
    "Mask": "combined",
    "Method": "aCompCor",
    "Retained": true,
    "SingularValue": 57.2658479505,
    "VarianceExplained": 0.0057645192
  },
  "a_comp_cor_31": {
    "CumulativeVarianceExplained": 0.2878942758,
    "Mask": "combined",
    "Method": "aCompCor",
    "Retained": true,
    "SingularValue": 57.0955481029,
    "VarianceExplained": 0.0057302846
  },
  "a_comp_cor_32": {
    "CumulativeVarianceExplained": 0.2936110615,
    "Mask": "combined",
    "Method": "aCompCor",
    "Retained": true,
    "SingularValue": 57.0282577741,
    "VarianceExplained": 0.0057167856
  },
  "a_comp_cor_33": {
    "CumulativeVarianceExplained": 0.2992654271,
    "Mask": "combined",
    "Method": "aCompCor",
    "Retained": true,
    "SingularValue": 56.7160653777,
    "VarianceExplained": 0.0056543656
  },
  "a_comp_cor_34": {
    "CumulativeVarianceExplained": 0.3048656409,
    "Mask": "combined",
    "Method": "aCompCor",
    "Retained": true,
    "SingularValue": 56.4438270688,
    "VarianceExplained": 0.0056002138
  },
  "a_comp_cor_35": {
    "CumulativeVarianceExplained": 0.3104170337,
    "Mask": "combined",
    "Method": "aCompCor",
    "Retained": true,
    "SingularValue": 56.1972584713,
    "VarianceExplained": 0.0055513928
  },
  "a_comp_cor_36": {
    "CumulativeVarianceExplained": 0.3159407081,
    "Mask": "combined",
    "Method": "aCompCor",
    "Retained": true,
    "SingularValue": 56.0567847207,
    "VarianceExplained": 0.0055236744
  },
  "a_comp_cor_37": {
    "CumulativeVarianceExplained": 0.3213906958,
    "Mask": "combined",
    "Method": "aCompCor",
    "Retained": true,
    "SingularValue": 55.6816261209,
    "VarianceExplained": 0.0054499877
  },
  "a_comp_cor_38": {
    "CumulativeVarianceExplained": 0.3268330117,
    "Mask": "combined",
    "Method": "aCompCor",
    "Retained": true,
    "SingularValue": 55.6424219071,
    "VarianceExplained": 0.0054423159
  },
  "a_comp_cor_39": {
    "CumulativeVarianceExplained": 0.3322512698,
    "Mask": "combined",
    "Method": "aCompCor",
    "Retained": true,
    "SingularValue": 55.5193017042,
    "VarianceExplained": 0.0054182581
  },
  "a_comp_cor_40": {
    "CumulativeVarianceExplained": 0.3376333561,
    "Mask": "combined",
    "Method": "aCompCor",
    "Retained": true,
    "SingularValue": 55.3336700654,
    "VarianceExplained": 0.0053820862
  },
  "a_comp_cor_41": {
    "CumulativeVarianceExplained": 0.3429763238,
    "Mask": "combined",
    "Method": "aCompCor",
    "Retained": true,
    "SingularValue": 55.1322129082,
    "VarianceExplained": 0.0053429677
  },
  "a_comp_cor_42": {
    "CumulativeVarianceExplained": 0.3483092973,
    "Mask": "combined",
    "Method": "aCompCor",
    "Retained": true,
    "SingularValue": 55.0806254606,
    "VarianceExplained": 0.0053329735
  },
  "a_comp_cor_43": {
    "CumulativeVarianceExplained": 0.3536155146,
    "Mask": "combined",
    "Method": "aCompCor",
    "Retained": true,
    "SingularValue": 54.9422783386,
    "VarianceExplained": 0.0053062173
  },
  "a_comp_cor_44": {
    "CumulativeVarianceExplained": 0.3588835635,
    "Mask": "combined",
    "Method": "aCompCor",
    "Retained": true,
    "SingularValue": 54.7443178988,
    "VarianceExplained": 0.0052680489
  },
  "a_comp_cor_45": {
    "CumulativeVarianceExplained": 0.3640860416,
    "Mask": "combined",
    "Method": "aCompCor",
    "Retained": true,
    "SingularValue": 54.4025528315,
    "VarianceExplained": 0.0052024781
  },
  "a_comp_cor_46": {
    "CumulativeVarianceExplained": 0.369267764,
    "Mask": "combined",
    "Method": "aCompCor",
    "Retained": true,
    "SingularValue": 54.2939227919,
    "VarianceExplained": 0.0051817224
  },
  "a_comp_cor_47": {
    "CumulativeVarianceExplained": 0.3744352072,
    "Mask": "combined",
    "Method": "aCompCor",
    "Retained": true,
    "SingularValue": 54.2190627465,
    "VarianceExplained": 0.0051674432
  },
  "a_comp_cor_48": {
    "CumulativeVarianceExplained": 0.3795843302,
    "Mask": "combined",
    "Method": "aCompCor",
    "Retained": true,
    "SingularValue": 54.1228658011,
    "VarianceExplained": 0.005149123
  },
  "a_comp_cor_49": {
    "CumulativeVarianceExplained": 0.3846875292,
    "Mask": "combined",
    "Method": "aCompCor",
    "Retained": true,
    "SingularValue": 53.8809695018,
    "VarianceExplained": 0.005103199
  },
  "a_comp_cor_50": {
    "CumulativeVarianceExplained": 0.3897666178,
    "Mask": "combined",
    "Method": "aCompCor",
    "Retained": true,
    "SingularValue": 53.7535366808,
    "VarianceExplained": 0.0050790886
  },
  "a_comp_cor_51": {
    "CumulativeVarianceExplained": 0.3948369523,
    "Mask": "combined",
    "Method": "aCompCor",
    "Retained": true,
    "SingularValue": 53.7071934177,
    "VarianceExplained": 0.0050703346
  },
  "a_comp_cor_52": {
    "CumulativeVarianceExplained": 0.399845348,
    "Mask": "combined",
    "Method": "aCompCor",
    "Retained": true,
    "SingularValue": 53.3781434258,
    "VarianceExplained": 0.0050083956
  },
  "a_comp_cor_53": {
    "CumulativeVarianceExplained": 0.4048233807,
    "Mask": "combined",
    "Method": "aCompCor",
    "Retained": true,
    "SingularValue": 53.216097337,
    "VarianceExplained": 0.0049780327
  },
  "a_comp_cor_54": {
    "CumulativeVarianceExplained": 0.4097772254,
    "Mask": "combined",
    "Method": "aCompCor",
    "Retained": true,
    "SingularValue": 53.0866530062,
    "VarianceExplained": 0.0049538447
  },
  "a_comp_cor_55": {
    "CumulativeVarianceExplained": 0.4146954332,
    "Mask": "combined",
    "Method": "aCompCor",
    "Retained": true,
    "SingularValue": 52.8953611478,
    "VarianceExplained": 0.0049182078
  },
  "a_comp_cor_56": {
    "CumulativeVarianceExplained": 0.4195991525,
    "Mask": "combined",
    "Method": "aCompCor",
    "Retained": true,
    "SingularValue": 52.8173918276,
    "VarianceExplained": 0.0049037193
  },
  "a_comp_cor_57": {
    "CumulativeVarianceExplained": 0.4244967044,
    "Mask": "combined",
    "Method": "aCompCor",
    "Retained": true,
    "SingularValue": 52.7841671262,
    "VarianceExplained": 0.0048975519
  },
  "a_comp_cor_58": {
    "CumulativeVarianceExplained": 0.429361654,
    "Mask": "combined",
    "Method": "aCompCor",
    "Retained": true,
    "SingularValue": 52.6081857803,
    "VarianceExplained": 0.0048649497
  },
  "a_comp_cor_59": {
    "CumulativeVarianceExplained": 0.4341957374,
    "Mask": "combined",
    "Method": "aCompCor",
    "Retained": true,
    "SingularValue": 52.4410305986,
    "VarianceExplained": 0.0048340834
  },
  "a_comp_cor_60": {
    "CumulativeVarianceExplained": 0.4390082404,
    "Mask": "combined",
    "Method": "aCompCor",
    "Retained": true,
    "SingularValue": 52.3238455209,
    "VarianceExplained": 0.004812503
  },
  "a_comp_cor_61": {
    "CumulativeVarianceExplained": 0.4438034334,
    "Mask": "combined",
    "Method": "aCompCor",
    "Retained": true,
    "SingularValue": 52.2296600037,
    "VarianceExplained": 0.0047951931
  },
  "a_comp_cor_62": {
    "CumulativeVarianceExplained": 0.4485816806,
    "Mask": "combined",
    "Method": "aCompCor",
    "Retained": true,
    "SingularValue": 52.137289973,
    "VarianceExplained": 0.0047782471
  },
  "a_comp_cor_63": {
    "CumulativeVarianceExplained": 0.4533246742,
    "Mask": "combined",
    "Method": "aCompCor",
    "Retained": true,
    "SingularValue": 51.9446017355,
    "VarianceExplained": 0.0047429936
  },
  "a_comp_cor_64": {
    "CumulativeVarianceExplained": 0.4580304845,
    "Mask": "combined",
    "Method": "aCompCor",
    "Retained": true,
    "SingularValue": 51.7405878687,
    "VarianceExplained": 0.0047058103
  },
  "a_comp_cor_65": {
    "CumulativeVarianceExplained": 0.4627296128,
    "Mask": "combined",
    "Method": "aCompCor",
    "Retained": true,
    "SingularValue": 51.7038402543,
    "VarianceExplained": 0.0046991283
  },
  "a_comp_cor_66": {
    "CumulativeVarianceExplained": 0.4674157692,
    "Mask": "combined",
    "Method": "aCompCor",
    "Retained": true,
    "SingularValue": 51.632427074,
    "VarianceExplained": 0.0046861564
  },
  "a_comp_cor_67": {
    "CumulativeVarianceExplained": 0.4720562206,
    "Mask": "combined",
    "Method": "aCompCor",
    "Retained": true,
    "SingularValue": 51.3800190967,
    "VarianceExplained": 0.0046404513
  },
  "a_comp_cor_68": {
    "CumulativeVarianceExplained": 0.476670987,
    "Mask": "combined",
    "Method": "aCompCor",
    "Retained": true,
    "SingularValue": 51.2376276623,
    "VarianceExplained": 0.0046147665
  },
  "a_comp_cor_69": {
    "CumulativeVarianceExplained": 0.4812668484,
    "Mask": "combined",
    "Method": "aCompCor",
    "Retained": true,
    "SingularValue": 51.1325685249,
    "VarianceExplained": 0.0045958614
  },
  "a_comp_cor_70": {
    "CumulativeVarianceExplained": 0.4858455737,
    "Mask": "combined",
    "Method": "aCompCor",
    "Retained": true,
    "SingularValue": 51.0371536646,
    "VarianceExplained": 0.0045787253
  },
  "a_comp_cor_71": {
    "CumulativeVarianceExplained": 0.4903898056,
    "Mask": "combined",
    "Method": "aCompCor",
    "Retained": true,
    "SingularValue": 50.8445480624,
    "VarianceExplained": 0.0045442319
  },
  "a_comp_cor_72": {
    "CumulativeVarianceExplained": 0.4949122397,
    "Mask": "combined",
    "Method": "aCompCor",
    "Retained": true,
    "SingularValue": 50.7224561071,
    "VarianceExplained": 0.0045224341
  },
  "a_comp_cor_73": {
    "CumulativeVarianceExplained": 0.4994122251,
    "Mask": "combined",
    "Method": "aCompCor",
    "Retained": true,
    "SingularValue": 50.5964095694,
    "VarianceExplained": 0.0044999853
  },
  "a_comp_cor_74": {
    "CumulativeVarianceExplained": 0.503870212,
    "Mask": "combined",
    "Method": "aCompCor",
    "Retained": true,
    "SingularValue": 50.3597475503,
    "VarianceExplained": 0.0044579869
  },
  "c_comp_cor_00": {
    "CumulativeVarianceExplained": 0.0968742643,
    "Mask": "CSF",
    "Method": "aCompCor",
    "Retained": true,
    "SingularValue": 96.7019789646,
    "VarianceExplained": 0.0968742643
  },
  "c_comp_cor_01": {
    "CumulativeVarianceExplained": 0.1717283888,
    "Mask": "CSF",
    "Method": "aCompCor",
    "Retained": true,
    "SingularValue": 85.0039330402,
    "VarianceExplained": 0.0748541244
  },
  "c_comp_cor_02": {
    "CumulativeVarianceExplained": 0.2447619536,
    "Mask": "CSF",
    "Method": "aCompCor",
    "Retained": true,
    "SingularValue": 83.9638613399,
    "VarianceExplained": 0.0730335648
  },
  "c_comp_cor_03": {
    "CumulativeVarianceExplained": 0.2908430523,
    "Mask": "CSF",
    "Method": "aCompCor",
    "Retained": true,
    "SingularValue": 66.6948908282,
    "VarianceExplained": 0.0460810988
  },
  "c_comp_cor_04": {
    "CumulativeVarianceExplained": 0.3284225902,
    "Mask": "CSF",
    "Method": "aCompCor",
    "Retained": true,
    "SingularValue": 60.2291689636,
    "VarianceExplained": 0.0375795379
  },
  "c_comp_cor_05": {
    "CumulativeVarianceExplained": 0.3636860032,
    "Mask": "CSF",
    "Method": "aCompCor",
    "Retained": true,
    "SingularValue": 58.3436136039,
    "VarianceExplained": 0.0352634129
  },
  "c_comp_cor_06": {
    "CumulativeVarianceExplained": 0.387339856,
    "Mask": "CSF",
    "Method": "aCompCor",
    "Retained": true,
    "SingularValue": 47.7839556111,
    "VarianceExplained": 0.0236538528
  },
  "c_comp_cor_07": {
    "CumulativeVarianceExplained": 0.4098271686,
    "Mask": "CSF",
    "Method": "aCompCor",
    "Retained": true,
    "SingularValue": 46.5907747491,
    "VarianceExplained": 0.0224873127
  },
  "c_comp_cor_08": {
    "CumulativeVarianceExplained": 0.4317801247,
    "Mask": "CSF",
    "Method": "aCompCor",
    "Retained": true,
    "SingularValue": 46.033887992,
    "VarianceExplained": 0.021952956
  },
  "c_comp_cor_09": {
    "CumulativeVarianceExplained": 0.4516021334,
    "Mask": "CSF",
    "Method": "aCompCor",
    "Retained": true,
    "SingularValue": 43.742639377,
    "VarianceExplained": 0.0198220087
  },
  "c_comp_cor_10": {
    "CumulativeVarianceExplained": 0.4703387641,
    "Mask": "CSF",
    "Method": "aCompCor",
    "Retained": true,
    "SingularValue": 42.5281902139,
    "VarianceExplained": 0.0187366307
  },
  "c_comp_cor_11": {
    "CumulativeVarianceExplained": 0.4877692783,
    "Mask": "CSF",
    "Method": "aCompCor",
    "Retained": true,
    "SingularValue": 41.0191118195,
    "VarianceExplained": 0.0174305142
  },
  "c_comp_cor_12": {
    "CumulativeVarianceExplained": 0.5043845347,
    "Mask": "CSF",
    "Method": "aCompCor",
    "Retained": true,
    "SingularValue": 40.048354545,
    "VarianceExplained": 0.0166152564
  },
  "dropped_0": {
    "CumulativeVarianceExplained": 0.4798554726,
    "Mask": "Edge",
    "Method": "EdgeRegressor",
    "Retained": false,
    "SingularValue": 165.9461849333,
    "VarianceExplained": 0.0059692276
  },
  "dropped_1": {
    "CumulativeVarianceExplained": 0.4855469764,
    "Mask": "Edge",
    "Method": "EdgeRegressor",
    "Retained": false,
    "SingularValue": 162.0398073495,
    "VarianceExplained": 0.0056915038
  },
  "dropped_10": {
    "CumulativeVarianceExplained": 0.5291887615,
    "Mask": "Edge",
    "Method": "EdgeRegressor",
    "Retained": false,
    "SingularValue": 140.8975219309,
    "VarianceExplained": 0.0043031879
  },
  "dropped_100": {
    "CumulativeVarianceExplained": 0.7818612542,
    "Mask": "Edge",
    "Method": "EdgeRegressor",
    "Retained": false,
    "SingularValue": 101.2616027776,
    "VarianceExplained": 0.0022226608
  },
  "dropped_101": {
    "CumulativeVarianceExplained": 0.7840757264,
    "Mask": "Edge",
    "Method": "EdgeRegressor",
    "Retained": false,
    "SingularValue": 101.0748998074,
    "VarianceExplained": 0.0022144722
  },
  "dropped_102": {
    "CumulativeVarianceExplained": 0.7862842679,
    "Mask": "Edge",
    "Method": "EdgeRegressor",
    "Retained": false,
    "SingularValue": 100.939462817,
    "VarianceExplained": 0.0022085415
  },
  "dropped_103": {
    "CumulativeVarianceExplained": 0.7884845184,
    "Mask": "Edge",
    "Method": "EdgeRegressor",
    "Retained": false,
    "SingularValue": 100.7498151605,
    "VarianceExplained": 0.0022002504
  },
  "dropped_104": {
    "CumulativeVarianceExplained": 0.7906815155,
    "Mask": "Edge",
    "Method": "EdgeRegressor",
    "Retained": false,
    "SingularValue": 100.6753031965,
    "VarianceExplained": 0.0021969971
  },
  "dropped_105": {
    "CumulativeVarianceExplained": 0.7928726252,
    "Mask": "Edge",
    "Method": "EdgeRegressor",
    "Retained": false,
    "SingularValue": 100.5403204006,
    "VarianceExplained": 0.0021911097
  },
  "dropped_106": {
    "CumulativeVarianceExplained": 0.7950526994,
    "Mask": "Edge",
    "Method": "EdgeRegressor",
    "Retained": false,
    "SingularValue": 100.2868143507,
    "VarianceExplained": 0.0021800742
  },
  "dropped_107": {
    "CumulativeVarianceExplained": 0.7972266229,
    "Mask": "Edge",
    "Method": "EdgeRegressor",
    "Retained": false,
    "SingularValue": 100.1452454624,
    "VarianceExplained": 0.0021739235
  },
  "dropped_108": {
    "CumulativeVarianceExplained": 0.7993970779,
    "Mask": "Edge",
    "Method": "EdgeRegressor",
    "Retained": false,
    "SingularValue": 100.0653222795,
    "VarianceExplained": 0.002170455
  },
  "dropped_109": {
    "CumulativeVarianceExplained": 0.8015645315,
    "Mask": "Edge",
    "Method": "EdgeRegressor",
    "Retained": false,
    "SingularValue": 99.9961085628,
    "VarianceExplained": 0.0021674535
  },
  "dropped_11": {
    "CumulativeVarianceExplained": 0.5334206413,
    "Mask": "Edge",
    "Method": "EdgeRegressor",
    "Retained": false,
    "SingularValue": 139.7252402346,
    "VarianceExplained": 0.0042318798
  },
  "dropped_110": {
    "CumulativeVarianceExplained": 0.8037194956,
    "Mask": "Edge",
    "Method": "EdgeRegressor",
    "Retained": false,
    "SingularValue": 99.7075910346,
    "VarianceExplained": 0.0021549641
  },
  "dropped_111": {
    "CumulativeVarianceExplained": 0.8058689015,
    "Mask": "Edge",
    "Method": "EdgeRegressor",
    "Retained": false,
    "SingularValue": 99.5789217099,
    "VarianceExplained": 0.0021494059
  },
  "dropped_112": {
    "CumulativeVarianceExplained": 0.8080155616,
    "Mask": "Edge",
    "Method": "EdgeRegressor",
    "Retained": false,
    "SingularValue": 99.5152985831,
    "VarianceExplained": 0.0021466602
  },
  "dropped_113": {
    "CumulativeVarianceExplained": 0.8101590337,
    "Mask": "Edge",
    "Method": "EdgeRegressor",
    "Retained": false,
    "SingularValue": 99.44137319,
    "VarianceExplained": 0.002143472
  },
  "dropped_114": {
    "CumulativeVarianceExplained": 0.8122929006,
    "Mask": "Edge",
    "Method": "EdgeRegressor",
    "Retained": false,
    "SingularValue": 99.2183187948,
    "VarianceExplained": 0.0021338669
  },
  "dropped_115": {
    "CumulativeVarianceExplained": 0.8144194208,
    "Mask": "Edge",
    "Method": "EdgeRegressor",
    "Retained": false,
    "SingularValue": 99.0473728749,
    "VarianceExplained": 0.0021265202
  },
  "dropped_116": {
    "CumulativeVarianceExplained": 0.8165390011,
    "Mask": "Edge",
    "Method": "EdgeRegressor",
    "Retained": false,
    "SingularValue": 98.8856199099,
    "VarianceExplained": 0.0021195803
  },
  "dropped_117": {
    "CumulativeVarianceExplained": 0.8186562186,
    "Mask": "Edge",
    "Method": "EdgeRegressor",
    "Retained": false,
    "SingularValue": 98.8304884821,
    "VarianceExplained": 0.0021172175
  },
  "dropped_118": {
    "CumulativeVarianceExplained": 0.8207664941,
    "Mask": "Edge",
    "Method": "EdgeRegressor",
    "Retained": false,
    "SingularValue": 98.6683302321,
    "VarianceExplained": 0.0021102755
  },
  "dropped_119": {
    "CumulativeVarianceExplained": 0.8228690681,
    "Mask": "Edge",
    "Method": "EdgeRegressor",
    "Retained": false,
    "SingularValue": 98.4881191584,
    "VarianceExplained": 0.002102574
  },
  "dropped_12": {
    "CumulativeVarianceExplained": 0.5375836978,
    "Mask": "Edge",
    "Method": "EdgeRegressor",
    "Retained": false,
    "SingularValue": 138.5844031229,
    "VarianceExplained": 0.0041630565
  },
  "dropped_120": {
    "CumulativeVarianceExplained": 0.8249668915,
    "Mask": "Edge",
    "Method": "EdgeRegressor",
    "Retained": false,
    "SingularValue": 98.3767946305,
    "VarianceExplained": 0.0020978234
  },
  "dropped_121": {
    "CumulativeVarianceExplained": 0.8270607143,
    "Mask": "Edge",
    "Method": "EdgeRegressor",
    "Retained": false,
    "SingularValue": 98.282944901,
    "VarianceExplained": 0.0020938228
  },
  "dropped_122": {
    "CumulativeVarianceExplained": 0.8291454604,
    "Mask": "Edge",
    "Method": "EdgeRegressor",
    "Retained": false,
    "SingularValue": 98.0696878453,
    "VarianceExplained": 0.0020847462
  },
  "dropped_123": {
    "CumulativeVarianceExplained": 0.831227566,
    "Mask": "Edge",
    "Method": "EdgeRegressor",
    "Retained": false,
    "SingularValue": 98.0075609181,
    "VarianceExplained": 0.0020821056
  },
  "dropped_124": {
    "CumulativeVarianceExplained": 0.8332987119,
    "Mask": "Edge",
    "Method": "EdgeRegressor",
    "Retained": false,
    "SingularValue": 97.7492762347,
    "VarianceExplained": 0.0020711459
  },
  "dropped_125": {
    "CumulativeVarianceExplained": 0.835364025,
    "Mask": "Edge",
    "Method": "EdgeRegressor",
    "Retained": false,
    "SingularValue": 97.6115352584,
    "VarianceExplained": 0.002065313
  },
  "dropped_126": {
    "CumulativeVarianceExplained": 0.8374247374,
    "Mask": "Edge",
    "Method": "EdgeRegressor",
    "Retained": false,
    "SingularValue": 97.5027575412,
    "VarianceExplained": 0.0020607124
  },
  "dropped_127": {
    "CumulativeVarianceExplained": 0.8394818068,
    "Mask": "Edge",
    "Method": "EdgeRegressor",
    "Retained": false,
    "SingularValue": 97.4165347473,
    "VarianceExplained": 0.0020570694
  },
  "dropped_128": {
    "CumulativeVarianceExplained": 0.8415296836,
    "Mask": "Edge",
    "Method": "EdgeRegressor",
    "Retained": false,
    "SingularValue": 97.1986217744,
    "VarianceExplained": 0.0020478767
  },
  "dropped_129": {
    "CumulativeVarianceExplained": 0.8435739182,
    "Mask": "Edge",
    "Method": "EdgeRegressor",
    "Retained": false,
    "SingularValue": 97.1121521637,
    "VarianceExplained": 0.0020442347
  },
  "dropped_13": {
    "CumulativeVarianceExplained": 0.541699717,
    "Mask": "Edge",
    "Method": "EdgeRegressor",
    "Retained": false,
    "SingularValue": 137.7992639758,
    "VarianceExplained": 0.0041160192
  },
  "dropped_130": {
    "CumulativeVarianceExplained": 0.8456159818,
    "Mask": "Edge",
    "Method": "EdgeRegressor",
    "Retained": false,
    "SingularValue": 97.0605681789,
    "VarianceExplained": 0.0020420636
  },
  "dropped_131": {
    "CumulativeVarianceExplained": 0.8476499761,
    "Mask": "Edge",
    "Method": "EdgeRegressor",
    "Retained": false,
    "SingularValue": 96.8686110942,
    "VarianceExplained": 0.0020339943
  },
  "dropped_132": {
    "CumulativeVarianceExplained": 0.8496779495,
    "Mask": "Edge",
    "Method": "EdgeRegressor",
    "Retained": false,
    "SingularValue": 96.7251303472,
    "VarianceExplained": 0.0020279733
  },
  "dropped_133": {
    "CumulativeVarianceExplained": 0.8517014191,
    "Mask": "Edge",
    "Method": "EdgeRegressor",
    "Retained": false,
    "SingularValue": 96.6176657649,
    "VarianceExplained": 0.0020234696
  },
  "dropped_134": {
    "CumulativeVarianceExplained": 0.8537216497,
    "Mask": "Edge",
    "Method": "EdgeRegressor",
    "Retained": false,
    "SingularValue": 96.5403089852,
    "VarianceExplained": 0.0020202307
  },
  "dropped_135": {
    "CumulativeVarianceExplained": 0.8557339248,
    "Mask": "Edge",
    "Method": "EdgeRegressor",
    "Retained": false,
    "SingularValue": 96.3500341979,
    "VarianceExplained": 0.002012275
  },
  "dropped_136": {
    "CumulativeVarianceExplained": 0.8577407936,
    "Mask": "Edge",
    "Method": "EdgeRegressor",
    "Retained": false,
    "SingularValue": 96.220518407,
    "VarianceExplained": 0.0020068688
  },
  "dropped_137": {
    "CumulativeVarianceExplained": 0.8597434113,
    "Mask": "Edge",
    "Method": "EdgeRegressor",
    "Retained": false,
    "SingularValue": 96.1185532838,
    "VarianceExplained": 0.0020026177
  },
  "dropped_138": {
    "CumulativeVarianceExplained": 0.8617420141,
    "Mask": "Edge",
    "Method": "EdgeRegressor",
    "Retained": false,
    "SingularValue": 96.0221565362,
    "VarianceExplained": 0.0019986029
  },
  "dropped_139": {
    "CumulativeVarianceExplained": 0.8637382754,
    "Mask": "Edge",
    "Method": "EdgeRegressor",
    "Retained": false,
    "SingularValue": 95.9658893931,
    "VarianceExplained": 0.0019962613
  },
  "dropped_14": {
    "CumulativeVarianceExplained": 0.5457280715,
    "Mask": "Edge",
    "Method": "EdgeRegressor",
    "Retained": false,
    "SingularValue": 136.3239130249,
    "VarianceExplained": 0.0040283545
  },
  "dropped_140": {
    "CumulativeVarianceExplained": 0.8657293201,
    "Mask": "Edge",
    "Method": "EdgeRegressor",
    "Retained": false,
    "SingularValue": 95.840419199,
    "VarianceExplained": 0.0019910447
  },
  "dropped_141": {
    "CumulativeVarianceExplained": 0.8677113214,
    "Mask": "Edge",
    "Method": "EdgeRegressor",
    "Retained": false,
    "SingularValue": 95.6225170241,
    "VarianceExplained": 0.0019820013
  },
  "dropped_142": {
    "CumulativeVarianceExplained": 0.8696885372,
    "Mask": "Edge",
    "Method": "EdgeRegressor",
    "Retained": false,
    "SingularValue": 95.5070083762,
    "VarianceExplained": 0.0019772158
  },
  "dropped_143": {
    "CumulativeVarianceExplained": 0.8716626735,
    "Mask": "Edge",
    "Method": "EdgeRegressor",
    "Retained": false,
    "SingularValue": 95.4326017334,
    "VarianceExplained": 0.0019741363
  },
  "dropped_144": {
    "CumulativeVarianceExplained": 0.8736345634,
    "Mask": "Edge",
    "Method": "EdgeRegressor",
    "Retained": false,
    "SingularValue": 95.3782906786,
    "VarianceExplained": 0.0019718899
  },
  "dropped_145": {
    "CumulativeVarianceExplained": 0.8755982693,
    "Mask": "Edge",
    "Method": "EdgeRegressor",
    "Retained": false,
    "SingularValue": 95.1801593025,
    "VarianceExplained": 0.0019637059
  },
  "dropped_146": {
    "CumulativeVarianceExplained": 0.8775589759,
    "Mask": "Edge",
    "Method": "EdgeRegressor",
    "Retained": false,
    "SingularValue": 95.1074427155,
    "VarianceExplained": 0.0019607066
  },
  "dropped_147": {
    "CumulativeVarianceExplained": 0.8795147588,
    "Mask": "Edge",
    "Method": "EdgeRegressor",
    "Retained": false,
    "SingularValue": 94.9879521512,
    "VarianceExplained": 0.0019557829
  },
  "dropped_148": {
    "CumulativeVarianceExplained": 0.8814681298,
    "Mask": "Edge",
    "Method": "EdgeRegressor",
    "Retained": false,
    "SingularValue": 94.9293636401,
    "VarianceExplained": 0.001953371
  },
  "dropped_149": {
    "CumulativeVarianceExplained": 0.8834099332,
    "Mask": "Edge",
    "Method": "EdgeRegressor",
    "Retained": false,
    "SingularValue": 94.6478671534,
    "VarianceExplained": 0.0019418034
  },
  "dropped_15": {
    "CumulativeVarianceExplained": 0.5496389512,
    "Mask": "Edge",
    "Method": "EdgeRegressor",
    "Retained": false,
    "SingularValue": 134.3214672896,
    "VarianceExplained": 0.0039108796
  },
  "dropped_150": {
    "CumulativeVarianceExplained": 0.8853450125,
    "Mask": "Edge",
    "Method": "EdgeRegressor",
    "Retained": false,
    "SingularValue": 94.4838503962,
    "VarianceExplained": 0.0019350793
  },
  "dropped_151": {
    "CumulativeVarianceExplained": 0.8872762667,
    "Mask": "Edge",
    "Method": "EdgeRegressor",
    "Retained": false,
    "SingularValue": 94.3904226892,
    "VarianceExplained": 0.0019312543
  },
  "dropped_152": {
    "CumulativeVarianceExplained": 0.8892020799,
    "Mask": "Edge",
    "Method": "EdgeRegressor",
    "Retained": false,
    "SingularValue": 94.2573607437,
    "VarianceExplained": 0.0019258131
  },
  "dropped_153": {
    "CumulativeVarianceExplained": 0.8911226174,
    "Mask": "Edge",
    "Method": "EdgeRegressor",
    "Retained": false,
    "SingularValue": 94.1281654297,
    "VarianceExplained": 0.0019205375
  },
  "dropped_154": {
    "CumulativeVarianceExplained": 0.8930415549,
    "Mask": "Edge",
    "Method": "EdgeRegressor",
    "Retained": false,
    "SingularValue": 94.0889508715,
    "VarianceExplained": 0.0019189376
  },
  "dropped_155": {
    "CumulativeVarianceExplained": 0.8949548948,
    "Mask": "Edge",
    "Method": "EdgeRegressor",
    "Retained": false,
    "SingularValue": 93.9516170681,
    "VarianceExplained": 0.0019133398
  },
  "dropped_156": {
    "CumulativeVarianceExplained": 0.8968626535,
    "Mask": "Edge",
    "Method": "EdgeRegressor",
    "Retained": false,
    "SingularValue": 93.8144901299,
    "VarianceExplained": 0.0019077587
  },
  "dropped_157": {
    "CumulativeVarianceExplained": 0.8987673349,
    "Mask": "Edge",
    "Method": "EdgeRegressor",
    "Retained": false,
    "SingularValue": 93.7387968697,
    "VarianceExplained": 0.0019046814
  },
  "dropped_158": {
    "CumulativeVarianceExplained": 0.9006707857,
    "Mask": "Edge",
    "Method": "EdgeRegressor",
    "Retained": false,
    "SingularValue": 93.7085090135,
    "VarianceExplained": 0.0019034508
  },
  "dropped_159": {
    "CumulativeVarianceExplained": 0.9025639269,
    "Mask": "Edge",
    "Method": "EdgeRegressor",
    "Retained": false,
    "SingularValue": 93.4543913096,
    "VarianceExplained": 0.0018931413
  },
  "dropped_16": {
    "CumulativeVarianceExplained": 0.5534988665,
    "Mask": "Edge",
    "Method": "EdgeRegressor",
    "Retained": false,
    "SingularValue": 133.4433968922,
    "VarianceExplained": 0.0038599153
  },
  "dropped_160": {
    "CumulativeVarianceExplained": 0.9044511093,
    "Mask": "Edge",
    "Method": "EdgeRegressor",
    "Retained": false,
    "SingularValue": 93.3071964061,
    "VarianceExplained": 0.0018871824
  },
  "dropped_161": {
    "CumulativeVarianceExplained": 0.9063364998,
    "Mask": "Edge",
    "Method": "EdgeRegressor",
    "Retained": false,
    "SingularValue": 93.2628870957,
    "VarianceExplained": 0.0018853905
  },
  "dropped_162": {
    "CumulativeVarianceExplained": 0.9082209424,
    "Mask": "Edge",
    "Method": "EdgeRegressor",
    "Retained": false,
    "SingularValue": 93.2394406484,
    "VarianceExplained": 0.0018844426
  },
  "dropped_163": {
    "CumulativeVarianceExplained": 0.9101010094,
    "Mask": "Edge",
    "Method": "EdgeRegressor",
    "Retained": false,
    "SingularValue": 93.1311279166,
    "VarianceExplained": 0.001880067
  },
  "dropped_164": {
    "CumulativeVarianceExplained": 0.9119747178,
    "Mask": "Edge",
    "Method": "EdgeRegressor",
    "Retained": false,
    "SingularValue": 92.9735061375,
    "VarianceExplained": 0.0018737084
  },
  "dropped_165": {
    "CumulativeVarianceExplained": 0.9138427105,
    "Mask": "Edge",
    "Method": "EdgeRegressor",
    "Retained": false,
    "SingularValue": 92.8315884806,
    "VarianceExplained": 0.0018679926
  },
  "dropped_166": {
    "CumulativeVarianceExplained": 0.9157060436,
    "Mask": "Edge",
    "Method": "EdgeRegressor",
    "Retained": false,
    "SingularValue": 92.7157365528,
    "VarianceExplained": 0.0018633331
  },
  "dropped_167": {
    "CumulativeVarianceExplained": 0.9175686361,
    "Mask": "Edge",
    "Method": "EdgeRegressor",
    "Retained": false,
    "SingularValue": 92.697309166,
    "VarianceExplained": 0.0018625925
  },
  "dropped_168": {
    "CumulativeVarianceExplained": 0.9194222589,
    "Mask": "Edge",
    "Method": "EdgeRegressor",
    "Retained": false,
    "SingularValue": 92.4738386099,
    "VarianceExplained": 0.0018536228
  },
  "dropped_169": {
    "CumulativeVarianceExplained": 0.9212705381,
    "Mask": "Edge",
    "Method": "EdgeRegressor",
    "Retained": false,
    "SingularValue": 92.3404507965,
    "VarianceExplained": 0.0018482792
  },
  "dropped_17": {
    "CumulativeVarianceExplained": 0.5572875135,
    "Mask": "Edge",
    "Method": "EdgeRegressor",
    "Retained": false,
    "SingularValue": 132.2057284964,
    "VarianceExplained": 0.003788647
  },
  "dropped_170": {
    "CumulativeVarianceExplained": 0.9231142933,
    "Mask": "Edge",
    "Method": "EdgeRegressor",
    "Retained": false,
    "SingularValue": 92.2273718419,
    "VarianceExplained": 0.0018437552
  },
  "dropped_171": {
    "CumulativeVarianceExplained": 0.9249542409,
    "Mask": "Edge",
    "Method": "EdgeRegressor",
    "Retained": false,
    "SingularValue": 92.1320915791,
    "VarianceExplained": 0.0018399476
  },
  "dropped_172": {
    "CumulativeVarianceExplained": 0.9267847278,
    "Mask": "Edge",
    "Method": "EdgeRegressor",
    "Retained": false,
    "SingularValue": 91.8949224452,
    "VarianceExplained": 0.0018304869
  },
  "dropped_173": {
    "CumulativeVarianceExplained": 0.9286077242,
    "Mask": "Edge",
    "Method": "EdgeRegressor",
    "Retained": false,
    "SingularValue": 91.7067076568,
    "VarianceExplained": 0.0018229964
  },
  "dropped_174": {
    "CumulativeVarianceExplained": 0.9304297826,
    "Mask": "Edge",
    "Method": "EdgeRegressor",
    "Retained": false,
    "SingularValue": 91.6831144039,
    "VarianceExplained": 0.0018220585
  },
  "dropped_175": {
    "CumulativeVarianceExplained": 0.9322467728,
    "Mask": "Edge",
    "Method": "EdgeRegressor",
    "Retained": false,
    "SingularValue": 91.5555108292,
    "VarianceExplained": 0.0018169902
  },
  "dropped_176": {
    "CumulativeVarianceExplained": 0.9340562142,
    "Mask": "Edge",
    "Method": "EdgeRegressor",
    "Retained": false,
    "SingularValue": 91.3651278499,
    "VarianceExplained": 0.0018094414
  },
  "dropped_177": {
    "CumulativeVarianceExplained": 0.9358592671,
    "Mask": "Edge",
    "Method": "EdgeRegressor",
    "Retained": false,
    "SingularValue": 91.2036937469,
    "VarianceExplained": 0.0018030528
  },
  "dropped_178": {
    "CumulativeVarianceExplained": 0.9376598199,
    "Mask": "Edge",
    "Method": "EdgeRegressor",
    "Retained": false,
    "SingularValue": 91.1404423839,
    "VarianceExplained": 0.0018005528
  },
  "dropped_179": {
    "CumulativeVarianceExplained": 0.9394525944,
    "Mask": "Edge",
    "Method": "EdgeRegressor",
    "Retained": false,
    "SingularValue": 90.9433696338,
    "VarianceExplained": 0.0017927746
  },
  "dropped_18": {
    "CumulativeVarianceExplained": 0.5609917859,
    "Mask": "Edge",
    "Method": "EdgeRegressor",
    "Retained": false,
    "SingularValue": 130.7253044479,
    "VarianceExplained": 0.0037042724
  },
  "dropped_180": {
    "CumulativeVarianceExplained": 0.9412395121,
    "Mask": "Edge",
    "Method": "EdgeRegressor",
    "Retained": false,
    "SingularValue": 90.794695899,
    "VarianceExplained": 0.0017869177
  },
  "dropped_181": {
    "CumulativeVarianceExplained": 0.9430218641,
    "Mask": "Edge",
    "Method": "EdgeRegressor",
    "Retained": false,
    "SingularValue": 90.6786289889,
    "VarianceExplained": 0.001782352
  },
  "dropped_182": {
    "CumulativeVarianceExplained": 0.9448022326,
    "Mask": "Edge",
    "Method": "EdgeRegressor",
    "Retained": false,
    "SingularValue": 90.6281564493,
    "VarianceExplained": 0.0017803684
  },
  "dropped_183": {
    "CumulativeVarianceExplained": 0.9465732809,
    "Mask": "Edge",
    "Method": "EdgeRegressor",
    "Retained": false,
    "SingularValue": 90.3906275345,
    "VarianceExplained": 0.0017710483
  },
  "dropped_184": {
    "CumulativeVarianceExplained": 0.9483397125,
    "Mask": "Edge",
    "Method": "EdgeRegressor",
    "Retained": false,
    "SingularValue": 90.2727379153,
    "VarianceExplained": 0.0017664316
  },
  "dropped_185": {
    "CumulativeVarianceExplained": 0.9500975867,
    "Mask": "Edge",
    "Method": "EdgeRegressor",
    "Retained": false,
    "SingularValue": 90.0538137051,
    "VarianceExplained": 0.0017578743
  },
  "dropped_186": {
    "CumulativeVarianceExplained": 0.951854165,
    "Mask": "Edge",
    "Method": "EdgeRegressor",
    "Retained": false,
    "SingularValue": 90.0206112557,
    "VarianceExplained": 0.0017565783
  },
  "dropped_187": {
    "CumulativeVarianceExplained": 0.9536043003,
    "Mask": "Edge",
    "Method": "EdgeRegressor",
    "Retained": false,
    "SingularValue": 89.8553653983,
    "VarianceExplained": 0.0017501353
  },
  "dropped_188": {
    "CumulativeVarianceExplained": 0.9553507105,
    "Mask": "Edge",
    "Method": "EdgeRegressor",
    "Retained": false,
    "SingularValue": 89.7596867064,
    "VarianceExplained": 0.0017464102
  },
  "dropped_189": {
    "CumulativeVarianceExplained": 0.9570906543,
    "Mask": "Edge",
    "Method": "EdgeRegressor",
    "Retained": false,
    "SingularValue": 89.5933581496,
    "VarianceExplained": 0.0017399438
  },
  "dropped_19": {
    "CumulativeVarianceExplained": 0.5646446342,
    "Mask": "Edge",
    "Method": "EdgeRegressor",
    "Retained": false,
    "SingularValue": 129.8147437381,
    "VarianceExplained": 0.0036528483
  },
  "dropped_190": {
    "CumulativeVarianceExplained": 0.9588278414,
    "Mask": "Edge",
    "Method": "EdgeRegressor",
    "Retained": false,
    "SingularValue": 89.5223544407,
    "VarianceExplained": 0.0017371871
  },
  "dropped_191": {
    "CumulativeVarianceExplained": 0.9605570379,
    "Mask": "Edge",
    "Method": "EdgeRegressor",
    "Retained": false,
    "SingularValue": 89.3162292314,
    "VarianceExplained": 0.0017291965
  },
  "dropped_192": {
    "CumulativeVarianceExplained": 0.9622829894,
    "Mask": "Edge",
    "Method": "EdgeRegressor",
    "Retained": false,
    "SingularValue": 89.2323837508,
    "VarianceExplained": 0.0017259515
  },
  "dropped_193": {
    "CumulativeVarianceExplained": 0.9640050316,
    "Mask": "Edge",
    "Method": "EdgeRegressor",
    "Retained": false,
    "SingularValue": 89.1312689276,
    "VarianceExplained": 0.0017220421
  },
  "dropped_194": {
    "CumulativeVarianceExplained": 0.9657224439,
    "Mask": "Edge",
    "Method": "EdgeRegressor",
    "Retained": false,
    "SingularValue": 89.0113725977,
    "VarianceExplained": 0.0017174124
  },
  "dropped_195": {
    "CumulativeVarianceExplained": 0.9674317699,
    "Mask": "Edge",
    "Method": "EdgeRegressor",
    "Retained": false,
    "SingularValue": 88.80156972,
    "VarianceExplained": 0.0017093259
  },
  "dropped_196": {
    "CumulativeVarianceExplained": 0.9691387438,
    "Mask": "Edge",
    "Method": "EdgeRegressor",
    "Retained": false,
    "SingularValue": 88.7404531722,
    "VarianceExplained": 0.0017069739
  },
  "dropped_197": {
    "CumulativeVarianceExplained": 0.9708384198,
    "Mask": "Edge",
    "Method": "EdgeRegressor",
    "Retained": false,
    "SingularValue": 88.5505526616,
    "VarianceExplained": 0.001699676
  },
  "dropped_198": {
    "CumulativeVarianceExplained": 0.9725272514,
    "Mask": "Edge",
    "Method": "EdgeRegressor",
    "Retained": false,
    "SingularValue": 88.2676118674,
    "VarianceExplained": 0.0016888316
  },
  "dropped_199": {
    "CumulativeVarianceExplained": 0.974210461,
    "Mask": "Edge",
    "Method": "EdgeRegressor",
    "Retained": false,
    "SingularValue": 88.1205706961,
    "VarianceExplained": 0.0016832096
  },
  "dropped_2": {
    "CumulativeVarianceExplained": 0.4910897267,
    "Mask": "Edge",
    "Method": "EdgeRegressor",
    "Retained": false,
    "SingularValue": 159.9082454422,
    "VarianceExplained": 0.0055427503
  },
  "dropped_20": {
    "CumulativeVarianceExplained": 0.5682477242,
    "Mask": "Edge",
    "Method": "EdgeRegressor",
    "Retained": false,
    "SingularValue": 128.927557732,
    "VarianceExplained": 0.00360309
  },
  "dropped_200": {
    "CumulativeVarianceExplained": 0.975886744,
    "Mask": "Edge",
    "Method": "EdgeRegressor",
    "Retained": false,
    "SingularValue": 87.9390698099,
    "VarianceExplained": 0.001676283
  },
  "dropped_201": {
    "CumulativeVarianceExplained": 0.9775566496,
    "Mask": "Edge",
    "Method": "EdgeRegressor",
    "Retained": false,
    "SingularValue": 87.7716310026,
    "VarianceExplained": 0.0016699056
  },
  "dropped_202": {
    "CumulativeVarianceExplained": 0.9792186496,
    "Mask": "Edge",
    "Method": "EdgeRegressor",
    "Retained": false,
    "SingularValue": 87.5636197439,
    "VarianceExplained": 0.001662
  },
  "dropped_203": {
    "CumulativeVarianceExplained": 0.9808763302,
    "Mask": "Edge",
    "Method": "EdgeRegressor",
    "Retained": false,
    "SingularValue": 87.4497620049,
    "VarianceExplained": 0.0016576806
  },
  "dropped_204": {
    "CumulativeVarianceExplained": 0.9825301606,
    "Mask": "Edge",
    "Method": "EdgeRegressor",
    "Retained": false,
    "SingularValue": 87.3481454632,
    "VarianceExplained": 0.0016538304
  },
  "dropped_205": {
    "CumulativeVarianceExplained": 0.9841816548,
    "Mask": "Edge",
    "Method": "EdgeRegressor",
    "Retained": false,
    "SingularValue": 87.2864302976,
    "VarianceExplained": 0.0016514942
  },
  "dropped_206": {
    "CumulativeVarianceExplained": 0.9858275452,
    "Mask": "Edge",
    "Method": "EdgeRegressor",
    "Retained": false,
    "SingularValue": 87.1382136374,
    "VarianceExplained": 0.0016458904
  },
  "dropped_207": {
    "CumulativeVarianceExplained": 0.98746819,
    "Mask": "Edge",
    "Method": "EdgeRegressor",
    "Retained": false,
    "SingularValue": 86.9992452355,
    "VarianceExplained": 0.0016406448
  },
  "dropped_208": {
    "CumulativeVarianceExplained": 0.9891024667,
    "Mask": "Edge",
    "Method": "EdgeRegressor",
    "Retained": false,
    "SingularValue": 86.8302402851,
    "VarianceExplained": 0.0016342767
  },
  "dropped_209": {
    "CumulativeVarianceExplained": 0.9907300815,
    "Mask": "Edge",
    "Method": "EdgeRegressor",
    "Retained": false,
    "SingularValue": 86.6530832413,
    "VarianceExplained": 0.0016276148
  },
  "dropped_21": {
    "CumulativeVarianceExplained": 0.5718151553,
    "Mask": "Edge",
    "Method": "EdgeRegressor",
    "Retained": false,
    "SingularValue": 128.2879904319,
    "VarianceExplained": 0.0035674311
  },
  "dropped_210": {
    "CumulativeVarianceExplained": 0.9923433862,
    "Mask": "Edge",
    "Method": "EdgeRegressor",
    "Retained": false,
    "SingularValue": 86.2713104885,
    "VarianceExplained": 0.0016133047
  },
  "dropped_211": {
    "CumulativeVarianceExplained": 0.9939501544,
    "Mask": "Edge",
    "Method": "EdgeRegressor",
    "Retained": false,
    "SingularValue": 86.0963640716,
    "VarianceExplained": 0.0016067682
  },
  "dropped_212": {
    "CumulativeVarianceExplained": 0.9955419582,
    "Mask": "Edge",
    "Method": "EdgeRegressor",
    "Retained": false,
    "SingularValue": 85.6945042575,
    "VarianceExplained": 0.0015918038
  },
  "dropped_213": {
    "CumulativeVarianceExplained": 0.9971218353,
    "Mask": "Edge",
    "Method": "EdgeRegressor",
    "Retained": false,
    "SingularValue": 85.3728656569,
    "VarianceExplained": 0.0015798771
  },
  "dropped_214": {
    "CumulativeVarianceExplained": 0.9986864178,
    "Mask": "Edge",
    "Method": "EdgeRegressor",
    "Retained": false,
    "SingularValue": 84.9586168253,
    "VarianceExplained": 0.0015645825
  },
  "dropped_215": {
    "CumulativeVarianceExplained": 1.0,
    "Mask": "Edge",
    "Method": "EdgeRegressor",
    "Retained": false,
    "SingularValue": 77.8460956008,
    "VarianceExplained": 0.0013135822
  },
  "dropped_216": {
    "CumulativeVarianceExplained": 1.0,
    "Mask": "Edge",
    "Method": "EdgeRegressor",
    "Retained": false,
    "SingularValue": 0.0,
    "VarianceExplained": 0.0
  },
  "dropped_217": {
    "CumulativeVarianceExplained": 1.0,
    "Mask": "Edge",
    "Method": "EdgeRegressor",
    "Retained": false,
    "SingularValue": 0.0,
    "VarianceExplained": 0.0
  },
  "dropped_218": {
    "CumulativeVarianceExplained": 1.0,
    "Mask": "Edge",
    "Method": "EdgeRegressor",
    "Retained": false,
    "SingularValue": 0.0,
    "VarianceExplained": 0.0
  },
  "dropped_219": {
    "CumulativeVarianceExplained": 1.0,
    "Mask": "Edge",
    "Method": "EdgeRegressor",
    "Retained": false,
    "SingularValue": 0.0,
    "VarianceExplained": 0.0
  },
  "dropped_22": {
    "CumulativeVarianceExplained": 0.5753565753,
    "Mask": "Edge",
    "Method": "EdgeRegressor",
    "Retained": false,
    "SingularValue": 127.8194424863,
    "VarianceExplained": 0.00354142
  },
  "dropped_220": {
    "CumulativeVarianceExplained": 1.0,
    "Mask": "Edge",
    "Method": "EdgeRegressor",
    "Retained": false,
    "SingularValue": 0.0,
    "VarianceExplained": 0.0
  },
  "dropped_23": {
    "CumulativeVarianceExplained": 0.5788440252,
    "Mask": "Edge",
    "Method": "EdgeRegressor",
    "Retained": false,
    "SingularValue": 126.8417395044,
    "VarianceExplained": 0.0034874499
  },
  "dropped_24": {
    "CumulativeVarianceExplained": 0.5822896132,
    "Mask": "Edge",
    "Method": "EdgeRegressor",
    "Retained": false,
    "SingularValue": 126.0781641904,
    "VarianceExplained": 0.003445588
  },
  "dropped_25": {
    "CumulativeVarianceExplained": 0.5857175497,
    "Mask": "Edge",
    "Method": "EdgeRegressor",
    "Retained": false,
    "SingularValue": 125.7548045037,
    "VarianceExplained": 0.0034279365
  },
  "dropped_26": {
    "CumulativeVarianceExplained": 0.5891038539,
    "Mask": "Edge",
    "Method": "EdgeRegressor",
    "Retained": false,
    "SingularValue": 124.9888263828,
    "VarianceExplained": 0.0033863043
  },
  "dropped_27": {
    "CumulativeVarianceExplained": 0.592422585,
    "Mask": "Edge",
    "Method": "EdgeRegressor",
    "Retained": false,
    "SingularValue": 123.735476385,
    "VarianceExplained": 0.0033187311
  },
  "dropped_28": {
    "CumulativeVarianceExplained": 0.5957119487,
    "Mask": "Edge",
    "Method": "EdgeRegressor",
    "Retained": false,
    "SingularValue": 123.186793211,
    "VarianceExplained": 0.0032893637
  },
  "dropped_29": {
    "CumulativeVarianceExplained": 0.5989609866,
    "Mask": "Edge",
    "Method": "EdgeRegressor",
    "Retained": false,
    "SingularValue": 122.4293621828,
    "VarianceExplained": 0.0032490378
  },
  "dropped_3": {
    "CumulativeVarianceExplained": 0.4963334437,
    "Mask": "Edge",
    "Method": "EdgeRegressor",
    "Retained": false,
    "SingularValue": 155.5348892477,
    "VarianceExplained": 0.005243717
  },
  "dropped_30": {
    "CumulativeVarianceExplained": 0.6021636905,
    "Mask": "Edge",
    "Method": "EdgeRegressor",
    "Retained": false,
    "SingularValue": 121.5532558761,
    "VarianceExplained": 0.0032027039
  },
  "dropped_31": {
    "CumulativeVarianceExplained": 0.6053376818,
    "Mask": "Edge",
    "Method": "EdgeRegressor",
    "Retained": false,
    "SingularValue": 121.0071610015,
    "VarianceExplained": 0.0031739914
  },
  "dropped_32": {
    "CumulativeVarianceExplained": 0.6084783203,
    "Mask": "Edge",
    "Method": "EdgeRegressor",
    "Retained": false,
    "SingularValue": 120.3696984613,
    "VarianceExplained": 0.0031406384
  },
  "dropped_33": {
    "CumulativeVarianceExplained": 0.6116022352,
    "Mask": "Edge",
    "Method": "EdgeRegressor",
    "Retained": false,
    "SingularValue": 120.0487948278,
    "VarianceExplained": 0.003123915
  },
  "dropped_34": {
    "CumulativeVarianceExplained": 0.6146663554,
    "Mask": "Edge",
    "Method": "EdgeRegressor",
    "Retained": false,
    "SingularValue": 118.894317573,
    "VarianceExplained": 0.0030641202
  },
  "dropped_35": {
    "CumulativeVarianceExplained": 0.6177235593,
    "Mask": "Edge",
    "Method": "EdgeRegressor",
    "Retained": false,
    "SingularValue": 118.7600597546,
    "VarianceExplained": 0.0030572039
  },
  "dropped_36": {
    "CumulativeVarianceExplained": 0.620738446,
    "Mask": "Edge",
    "Method": "EdgeRegressor",
    "Retained": false,
    "SingularValue": 117.9352676177,
    "VarianceExplained": 0.0030148867
  },
  "dropped_37": {
    "CumulativeVarianceExplained": 0.623721787,
    "Mask": "Edge",
    "Method": "EdgeRegressor",
    "Retained": false,
    "SingularValue": 117.3166489284,
    "VarianceExplained": 0.002983341
  },
  "dropped_38": {
    "CumulativeVarianceExplained": 0.6266654561,
    "Mask": "Edge",
    "Method": "EdgeRegressor",
    "Retained": false,
    "SingularValue": 116.5340113667,
    "VarianceExplained": 0.0029436691
  },
  "dropped_39": {
    "CumulativeVarianceExplained": 0.6296000257,
    "Mask": "Edge",
    "Method": "EdgeRegressor",
    "Retained": false,
    "SingularValue": 116.3537569421,
    "VarianceExplained": 0.0029345696
  },
  "dropped_4": {
    "CumulativeVarianceExplained": 0.5015155496,
    "Mask": "Edge",
    "Method": "EdgeRegressor",
    "Retained": false,
    "SingularValue": 154.6184606144,
    "VarianceExplained": 0.0051821059
  },
  "dropped_40": {
    "CumulativeVarianceExplained": 0.6325167586,
    "Mask": "Edge",
    "Method": "EdgeRegressor",
    "Retained": false,
    "SingularValue": 115.9996113143,
    "VarianceExplained": 0.0029167329
  },
  "dropped_41": {
    "CumulativeVarianceExplained": 0.6354047909,
    "Mask": "Edge",
    "Method": "EdgeRegressor",
    "Retained": false,
    "SingularValue": 115.427482075,
    "VarianceExplained": 0.0028880323
  },
  "dropped_42": {
    "CumulativeVarianceExplained": 0.638278287,
    "Mask": "Edge",
    "Method": "EdgeRegressor",
    "Retained": false,
    "SingularValue": 115.1366296336,
    "VarianceExplained": 0.0028734962
  },
  "dropped_43": {
    "CumulativeVarianceExplained": 0.6411385753,
    "Mask": "Edge",
    "Method": "EdgeRegressor",
    "Retained": false,
    "SingularValue": 114.8717142671,
    "VarianceExplained": 0.0028602882
  },
  "dropped_44": {
    "CumulativeVarianceExplained": 0.6439788615,
    "Mask": "Edge",
    "Method": "EdgeRegressor",
    "Retained": false,
    "SingularValue": 114.4693614945,
    "VarianceExplained": 0.0028402863
  },
  "dropped_45": {
    "CumulativeVarianceExplained": 0.6467818944,
    "Mask": "Edge",
    "Method": "EdgeRegressor",
    "Retained": false,
    "SingularValue": 113.7161883663,
    "VarianceExplained": 0.0028030328
  },
  "dropped_46": {
    "CumulativeVarianceExplained": 0.6495537384,
    "Mask": "Edge",
    "Method": "EdgeRegressor",
    "Retained": false,
    "SingularValue": 113.0817690029,
    "VarianceExplained": 0.002771844
  },
  "dropped_47": {
    "CumulativeVarianceExplained": 0.6523110571,
    "Mask": "Edge",
    "Method": "EdgeRegressor",
    "Retained": false,
    "SingularValue": 112.7850893737,
    "VarianceExplained": 0.0027573187
  },
  "dropped_48": {
    "CumulativeVarianceExplained": 0.6550656192,
    "Mask": "Edge",
    "Method": "EdgeRegressor",
    "Retained": false,
    "SingularValue": 112.7286969679,
    "VarianceExplained": 0.0027545621
  },
  "dropped_49": {
    "CumulativeVarianceExplained": 0.6577962515,
    "Mask": "Edge",
    "Method": "EdgeRegressor",
    "Retained": false,
    "SingularValue": 112.2379716698,
    "VarianceExplained": 0.0027306322
  },
  "dropped_5": {
    "CumulativeVarianceExplained": 0.5064289209,
    "Mask": "Edge",
    "Method": "EdgeRegressor",
    "Retained": false,
    "SingularValue": 150.5559743244,
    "VarianceExplained": 0.0049133713
  },
  "dropped_50": {
    "CumulativeVarianceExplained": 0.6605154039,
    "Mask": "Edge",
    "Method": "EdgeRegressor",
    "Retained": false,
    "SingularValue": 112.0017947715,
    "VarianceExplained": 0.0027191525
  },
  "dropped_51": {
    "CumulativeVarianceExplained": 0.6632111085,
    "Mask": "Edge",
    "Method": "EdgeRegressor",
    "Retained": false,
    "SingularValue": 111.5178405473,
    "VarianceExplained": 0.0026957046
  },
  "dropped_52": {
    "CumulativeVarianceExplained": 0.6658934332,
    "Mask": "Edge",
    "Method": "EdgeRegressor",
    "Retained": false,
    "SingularValue": 111.2407406609,
    "VarianceExplained": 0.0026823246
  },
  "dropped_53": {
    "CumulativeVarianceExplained": 0.668563147,
    "Mask": "Edge",
    "Method": "EdgeRegressor",
    "Retained": false,
    "SingularValue": 110.9789357915,
    "VarianceExplained": 0.0026697138
  },
  "dropped_54": {
    "CumulativeVarianceExplained": 0.6712182595,
    "Mask": "Edge",
    "Method": "EdgeRegressor",
    "Retained": false,
    "SingularValue": 110.6750344622,
    "VarianceExplained": 0.0026551125
  },
  "dropped_55": {
    "CumulativeVarianceExplained": 0.6738588838,
    "Mask": "Edge",
    "Method": "EdgeRegressor",
    "Retained": false,
    "SingularValue": 110.3726602018,
    "VarianceExplained": 0.0026406243
  },
  "dropped_56": {
    "CumulativeVarianceExplained": 0.6764827891,
    "Mask": "Edge",
    "Method": "EdgeRegressor",
    "Retained": false,
    "SingularValue": 110.0226953241,
    "VarianceExplained": 0.0026239053
  },
  "dropped_57": {
    "CumulativeVarianceExplained": 0.6790954591,
    "Mask": "Edge",
    "Method": "EdgeRegressor",
    "Retained": false,
    "SingularValue": 109.7868896668,
    "VarianceExplained": 0.00261267
  },
  "dropped_58": {
    "CumulativeVarianceExplained": 0.6816939641,
    "Mask": "Edge",
    "Method": "EdgeRegressor",
    "Retained": false,
    "SingularValue": 109.4888726944,
    "VarianceExplained": 0.002598505
  },
  "dropped_59": {
    "CumulativeVarianceExplained": 0.6842811835,
    "Mask": "Edge",
    "Method": "EdgeRegressor",
    "Retained": false,
    "SingularValue": 109.2508511993,
    "VarianceExplained": 0.0025872194
  },
  "dropped_6": {
    "CumulativeVarianceExplained": 0.5112503592,
    "Mask": "Edge",
    "Method": "EdgeRegressor",
    "Retained": false,
    "SingularValue": 149.1408144459,
    "VarianceExplained": 0.0048214383
  },
  "dropped_60": {
    "CumulativeVarianceExplained": 0.686859013,
    "Mask": "Edge",
    "Method": "EdgeRegressor",
    "Retained": false,
    "SingularValue": 109.0524183558,
    "VarianceExplained": 0.0025778295
  },
  "dropped_61": {
    "CumulativeVarianceExplained": 0.6894050942,
    "Mask": "Edge",
    "Method": "EdgeRegressor",
    "Retained": false,
    "SingularValue": 108.3787969007,
    "VarianceExplained": 0.0025460812
  },
  "dropped_62": {
    "CumulativeVarianceExplained": 0.6919467705,
    "Mask": "Edge",
    "Method": "EdgeRegressor",
    "Retained": false,
    "SingularValue": 108.2850045005,
    "VarianceExplained": 0.0025416763
  },
  "dropped_63": {
    "CumulativeVarianceExplained": 0.694476192,
    "Mask": "Edge",
    "Method": "EdgeRegressor",
    "Retained": false,
    "SingularValue": 108.0236404469,
    "VarianceExplained": 0.0025294215
  },
  "dropped_64": {
    "CumulativeVarianceExplained": 0.6969964971,
    "Mask": "Edge",
    "Method": "EdgeRegressor",
    "Retained": false,
    "SingularValue": 107.828796674,
    "VarianceExplained": 0.0025203051
  },
  "dropped_65": {
    "CumulativeVarianceExplained": 0.6995026126,
    "Mask": "Edge",
    "Method": "EdgeRegressor",
    "Retained": false,
    "SingularValue": 107.5248240786,
    "VarianceExplained": 0.0025061155
  },
  "dropped_66": {
    "CumulativeVarianceExplained": 0.702004789,
    "Mask": "Edge",
    "Method": "EdgeRegressor",
    "Retained": false,
    "SingularValue": 107.4402888994,
    "VarianceExplained": 0.0025021764
  },
  "dropped_67": {
    "CumulativeVarianceExplained": 0.7044993525,
    "Mask": "Edge",
    "Method": "EdgeRegressor",
    "Retained": false,
    "SingularValue": 107.2767194568,
    "VarianceExplained": 0.0024945635
  },
  "dropped_68": {
    "CumulativeVarianceExplained": 0.7069828881,
    "Mask": "Edge",
    "Method": "EdgeRegressor",
    "Retained": false,
    "SingularValue": 107.0393332364,
    "VarianceExplained": 0.0024835356
  },
  "dropped_69": {
    "CumulativeVarianceExplained": 0.7094533902,
    "Mask": "Edge",
    "Method": "EdgeRegressor",
    "Retained": false,
    "SingularValue": 106.758094714,
    "VarianceExplained": 0.0024705021
  },
  "dropped_7": {
    "CumulativeVarianceExplained": 0.5159418481,
    "Mask": "Edge",
    "Method": "EdgeRegressor",
    "Retained": false,
    "SingularValue": 147.117232737,
    "VarianceExplained": 0.0046914889
  },
  "dropped_70": {
    "CumulativeVarianceExplained": 0.7119216899,
    "Mask": "Edge",
    "Method": "EdgeRegressor",
    "Retained": false,
    "SingularValue": 106.710498684,
    "VarianceExplained": 0.0024682997
  },
  "dropped_71": {
    "CumulativeVarianceExplained": 0.7143838654,
    "Mask": "Edge",
    "Method": "EdgeRegressor",
    "Retained": false,
    "SingularValue": 106.5780346189,
    "VarianceExplained": 0.0024621755
  },
  "dropped_72": {
    "CumulativeVarianceExplained": 0.7168319178,
    "Mask": "Edge",
    "Method": "EdgeRegressor",
    "Retained": false,
    "SingularValue": 106.2719262608,
    "VarianceExplained": 0.0024480524
  },
  "dropped_73": {
    "CumulativeVarianceExplained": 0.7192705595,
    "Mask": "Edge",
    "Method": "EdgeRegressor",
    "Retained": false,
    "SingularValue": 106.0674677214,
    "VarianceExplained": 0.0024386417
  },
  "dropped_74": {
    "CumulativeVarianceExplained": 0.7216891714,
    "Mask": "Edge",
    "Method": "EdgeRegressor",
    "Retained": false,
    "SingularValue": 105.6309780748,
    "VarianceExplained": 0.002418612
  },
  "dropped_75": {
    "CumulativeVarianceExplained": 0.7240992308,
    "Mask": "Edge",
    "Method": "EdgeRegressor",
    "Retained": false,
    "SingularValue": 105.4440491106,
    "VarianceExplained": 0.0024100594
  },
  "dropped_76": {
    "CumulativeVarianceExplained": 0.726500437,
    "Mask": "Edge",
    "Method": "EdgeRegressor",
    "Retained": false,
    "SingularValue": 105.2501986552,
    "VarianceExplained": 0.0024012061
  },
  "dropped_77": {
    "CumulativeVarianceExplained": 0.7288998604,
    "Mask": "Edge",
    "Method": "EdgeRegressor",
    "Retained": false,
    "SingularValue": 105.2111216568,
    "VarianceExplained": 0.0023994234
  },
  "dropped_78": {
    "CumulativeVarianceExplained": 0.7312885999,
    "Mask": "Edge",
    "Method": "EdgeRegressor",
    "Retained": false,
    "SingularValue": 104.9766227441,
    "VarianceExplained": 0.0023887395
  },
  "dropped_79": {
    "CumulativeVarianceExplained": 0.7336648653,
    "Mask": "Edge",
    "Method": "EdgeRegressor",
    "Retained": false,
    "SingularValue": 104.7021683083,
    "VarianceExplained": 0.0023762654
  },
  "dropped_8": {
    "CumulativeVarianceExplained": 0.5204596966,
    "Mask": "Edge",
    "Method": "EdgeRegressor",
    "Retained": false,
    "SingularValue": 144.3690288502,
    "VarianceExplained": 0.0045178485
  },
  "dropped_80": {
    "CumulativeVarianceExplained": 0.7360317178,
    "Mask": "Edge",
    "Method": "EdgeRegressor",
    "Retained": false,
    "SingularValue": 104.4945893152,
    "VarianceExplained": 0.0023668525
  },
  "dropped_81": {
    "CumulativeVarianceExplained": 0.7383903235,
    "Mask": "Edge",
    "Method": "EdgeRegressor",
    "Retained": false,
    "SingularValue": 104.3123835045,
    "VarianceExplained": 0.0023586056
  },
  "dropped_82": {
    "CumulativeVarianceExplained": 0.7407366954,
    "Mask": "Edge",
    "Method": "EdgeRegressor",
    "Retained": false,
    "SingularValue": 104.041506248,
    "VarianceExplained": 0.0023463719
  },
  "dropped_83": {
    "CumulativeVarianceExplained": 0.743078684,
    "Mask": "Edge",
    "Method": "EdgeRegressor",
    "Retained": false,
    "SingularValue": 103.9442779895,
    "VarianceExplained": 0.0023419886
  },
  "dropped_84": {
    "CumulativeVarianceExplained": 0.7454183952,
    "Mask": "Edge",
    "Method": "EdgeRegressor",
    "Retained": false,
    "SingularValue": 103.893728777,
    "VarianceExplained": 0.0023397112
  },
  "dropped_85": {
    "CumulativeVarianceExplained": 0.7477529389,
    "Mask": "Edge",
    "Method": "EdgeRegressor",
    "Retained": false,
    "SingularValue": 103.7789326806,
    "VarianceExplained": 0.0023345436
  },
  "dropped_86": {
    "CumulativeVarianceExplained": 0.750075732,
    "Mask": "Edge",
    "Method": "EdgeRegressor",
    "Retained": false,
    "SingularValue": 103.5174264565,
    "VarianceExplained": 0.0023227931
  },
  "dropped_87": {
    "CumulativeVarianceExplained": 0.7523938197,
    "Mask": "Edge",
    "Method": "EdgeRegressor",
    "Retained": false,
    "SingularValue": 103.4125236559,
    "VarianceExplained": 0.0023180877
  },
  "dropped_88": {
    "CumulativeVarianceExplained": 0.7547070404,
    "Mask": "Edge",
    "Method": "EdgeRegressor",
    "Retained": false,
    "SingularValue": 103.3039033974,
    "VarianceExplained": 0.0023132206
  },
  "dropped_89": {
    "CumulativeVarianceExplained": 0.7570077825,
    "Mask": "Edge",
    "Method": "EdgeRegressor",
    "Retained": false,
    "SingularValue": 103.0248947207,
    "VarianceExplained": 0.0023007422
  },
  "dropped_9": {
    "CumulativeVarianceExplained": 0.5248855736,
    "Mask": "Edge",
    "Method": "EdgeRegressor",
    "Retained": false,
    "SingularValue": 142.8919869724,
    "VarianceExplained": 0.0044258771
  },
  "dropped_90": {
    "CumulativeVarianceExplained": 0.759305018,
    "Mask": "Edge",
    "Method": "EdgeRegressor",
    "Retained": false,
    "SingularValue": 102.9463513508,
    "VarianceExplained": 0.0022972355
  },
  "dropped_91": {
    "CumulativeVarianceExplained": 0.7615907368,
    "Mask": "Edge",
    "Method": "EdgeRegressor",
    "Retained": false,
    "SingularValue": 102.6879779741,
    "VarianceExplained": 0.0022857188
  },
  "dropped_92": {
    "CumulativeVarianceExplained": 0.7638753365,
    "Mask": "Edge",
    "Method": "EdgeRegressor",
    "Retained": false,
    "SingularValue": 102.6628362781,
    "VarianceExplained": 0.0022845997
  },
  "dropped_93": {
    "CumulativeVarianceExplained": 0.7661511586,
    "Mask": "Edge",
    "Method": "EdgeRegressor",
    "Retained": false,
    "SingularValue": 102.4654273663,
    "VarianceExplained": 0.0022758221
  },
  "dropped_94": {
    "CumulativeVarianceExplained": 0.7684191585,
    "Mask": "Edge",
    "Method": "EdgeRegressor",
    "Retained": false,
    "SingularValue": 102.2891861724,
    "VarianceExplained": 0.002268
  },
  "dropped_95": {
    "CumulativeVarianceExplained": 0.7706775212,
    "Mask": "Edge",
    "Method": "EdgeRegressor",
    "Retained": false,
    "SingularValue": 102.0716286996,
    "VarianceExplained": 0.0022583627
  },
  "dropped_96": {
    "CumulativeVarianceExplained": 0.7729291454,
    "Mask": "Edge",
    "Method": "EdgeRegressor",
    "Retained": false,
    "SingularValue": 101.9192358921,
    "VarianceExplained": 0.0022516242
  },
  "dropped_97": {
    "CumulativeVarianceExplained": 0.7751779514,
    "Mask": "Edge",
    "Method": "EdgeRegressor",
    "Retained": false,
    "SingularValue": 101.8554318345,
    "VarianceExplained": 0.002248806
  },
  "dropped_98": {
    "CumulativeVarianceExplained": 0.7774097819,
    "Mask": "Edge",
    "Method": "EdgeRegressor",
    "Retained": false,
    "SingularValue": 101.470268991,
    "VarianceExplained": 0.0022318306
  },
  "dropped_99": {
    "CumulativeVarianceExplained": 0.7796385934,
    "Mask": "Edge",
    "Method": "EdgeRegressor",
    "Retained": false,
    "SingularValue": 101.4016137594,
    "VarianceExplained": 0.0022288114
  },
  "edge_comp_00": {
    "CumulativeVarianceExplained": 0.0869756832,
    "Mask": "Edge",
    "Method": "EdgeRegressor",
    "Retained": true,
    "SingularValue": 633.4423953732,
    "VarianceExplained": 0.0869756832
  },
  "edge_comp_01": {
    "CumulativeVarianceExplained": 0.1414203534,
    "Mask": "Edge",
    "Method": "EdgeRegressor",
    "Retained": true,
    "SingularValue": 501.1709479627,
    "VarianceExplained": 0.0544446702
  },
  "edge_comp_02": {
    "CumulativeVarianceExplained": 0.1841542431,
    "Mask": "Edge",
    "Method": "EdgeRegressor",
    "Retained": true,
    "SingularValue": 444.0117003207,
    "VarianceExplained": 0.0427338897
  },
  "edge_comp_03": {
    "CumulativeVarianceExplained": 0.2166463349,
    "Mask": "Edge",
    "Method": "EdgeRegressor",
    "Retained": true,
    "SingularValue": 387.1658451267,
    "VarianceExplained": 0.0324920918
  },
  "edge_comp_04": {
    "CumulativeVarianceExplained": 0.2449565277,
    "Mask": "Edge",
    "Method": "EdgeRegressor",
    "Retained": true,
    "SingularValue": 361.3928995653,
    "VarianceExplained": 0.0283101928
  },
  "edge_comp_05": {
    "CumulativeVarianceExplained": 0.272412898,
    "Mask": "Edge",
    "Method": "EdgeRegressor",
    "Retained": true,
    "SingularValue": 355.901455407,
    "VarianceExplained": 0.0274563703
  },
  "edge_comp_06": {
    "CumulativeVarianceExplained": 0.2937088066,
    "Mask": "Edge",
    "Method": "EdgeRegressor",
    "Retained": true,
    "SingularValue": 313.4413506888,
    "VarianceExplained": 0.0212959087
  },
  "edge_comp_07": {
    "CumulativeVarianceExplained": 0.3140257222,
    "Mask": "Edge",
    "Method": "EdgeRegressor",
    "Retained": true,
    "SingularValue": 306.1519921507,
    "VarianceExplained": 0.0203169155
  },
  "edge_comp_08": {
    "CumulativeVarianceExplained": 0.3309179829,
    "Mask": "Edge",
    "Method": "EdgeRegressor",
    "Retained": true,
    "SingularValue": 279.1592928341,
    "VarianceExplained": 0.0168922607
  },
  "edge_comp_09": {
    "CumulativeVarianceExplained": 0.3462746352,
    "Mask": "Edge",
    "Method": "EdgeRegressor",
    "Retained": true,
    "SingularValue": 266.1683905425,
    "VarianceExplained": 0.0153566524
  },
  "edge_comp_10": {
    "CumulativeVarianceExplained": 0.3606309015,
    "Mask": "Edge",
    "Method": "EdgeRegressor",
    "Retained": true,
    "SingularValue": 257.352833751,
    "VarianceExplained": 0.0143562663
  },
  "edge_comp_11": {
    "CumulativeVarianceExplained": 0.3730983517,
    "Mask": "Edge",
    "Method": "EdgeRegressor",
    "Retained": true,
    "SingularValue": 239.8264196402,
    "VarianceExplained": 0.0124674502
  },
  "edge_comp_12": {
    "CumulativeVarianceExplained": 0.3843438284,
    "Mask": "Edge",
    "Method": "EdgeRegressor",
    "Retained": true,
    "SingularValue": 227.7703227266,
    "VarianceExplained": 0.0112454767
  },
  "edge_comp_13": {
    "CumulativeVarianceExplained": 0.3954308246,
    "Mask": "Edge",
    "Method": "EdgeRegressor",
    "Retained": true,
    "SingularValue": 226.1596644806,
    "VarianceExplained": 0.0110869962
  },
  "edge_comp_14": {
    "CumulativeVarianceExplained": 0.4060302666,
    "Mask": "Edge",
    "Method": "EdgeRegressor",
    "Retained": true,
    "SingularValue": 221.1310377082,
    "VarianceExplained": 0.010599442
  },
  "edge_comp_15": {
    "CumulativeVarianceExplained": 0.4152922793,
    "Mask": "Edge",
    "Method": "EdgeRegressor",
    "Retained": true,
    "SingularValue": 206.7097153539,
    "VarianceExplained": 0.0092620127
  },
  "edge_comp_16": {
    "CumulativeVarianceExplained": 0.4238277129,
    "Mask": "Edge",
    "Method": "EdgeRegressor",
    "Retained": true,
    "SingularValue": 198.4362430424,
    "VarianceExplained": 0.0085354336
  },
  "edge_comp_17": {
    "CumulativeVarianceExplained": 0.4320900721,
    "Mask": "Edge",
    "Method": "EdgeRegressor",
    "Retained": true,
    "SingularValue": 195.2361510679,
    "VarianceExplained": 0.0082623592
  },
  "edge_comp_18": {
    "CumulativeVarianceExplained": 0.4399916152,
    "Mask": "Edge",
    "Method": "EdgeRegressor",
    "Retained": true,
    "SingularValue": 190.9255971438,
    "VarianceExplained": 0.0079015431
  },
  "edge_comp_19": {
    "CumulativeVarianceExplained": 0.4472642623,
    "Mask": "Edge",
    "Method": "EdgeRegressor",
    "Retained": true,
    "SingularValue": 183.1700481151,
    "VarianceExplained": 0.0072726471
  },
  "edge_comp_20": {
    "CumulativeVarianceExplained": 0.454493706,
    "Mask": "Edge",
    "Method": "EdgeRegressor",
    "Retained": true,
    "SingularValue": 182.6251735084,
    "VarianceExplained": 0.0072294437
  },
  "edge_comp_21": {
    "CumulativeVarianceExplained": 0.4612237096,
    "Mask": "Edge",
    "Method": "EdgeRegressor",
    "Retained": true,
    "SingularValue": 176.2040356838,
    "VarianceExplained": 0.0067300036
  },
  "edge_comp_22": {
    "CumulativeVarianceExplained": 0.4677139595,
    "Mask": "Edge",
    "Method": "EdgeRegressor",
    "Retained": true,
    "SingularValue": 173.0369744019,
    "VarianceExplained": 0.0064902499
  },
  "edge_comp_23": {
    "CumulativeVarianceExplained": 0.4738862449,
    "Mask": "Edge",
    "Method": "EdgeRegressor",
    "Retained": true,
    "SingularValue": 168.745112674,
    "VarianceExplained": 0.0061722854
  },
  "framewise_displacement": {
    "Units": "mm"
  },
  "rot_x": {
    "Description": "Rotation about left-right axis. Also known as \"pitch\".",
    "Units": "rad"
  },
  "rot_y": {
    "Description": "Rotation about anterior-posterior axis. Also known as \"roll\".",
    "Units": "rad"
  },
  "rot_z": {
    "Description": "Rotation about superior-inferior axis. Also known as \"yaw\".",
    "Units": "rad"
  },
  "t_comp_cor_00": {
    "CumulativeVarianceExplained": 0.1461030242,
    "Method": "tCompCor",
    "Retained": true,
    "SingularValue": 236.9867781793,
    "VarianceExplained": 0.1461030242
  },
  "t_comp_cor_01": {
    "CumulativeVarianceExplained": 0.2768049664,
    "Method": "tCompCor",
    "Retained": true,
    "SingularValue": 224.148343884,
    "VarianceExplained": 0.1307019421
  },
  "t_comp_cor_02": {
    "CumulativeVarianceExplained": 0.3604856916,
    "Method": "tCompCor",
    "Retained": true,
    "SingularValue": 179.352416126,
    "VarianceExplained": 0.0836807252
  },
  "t_comp_cor_03": {
    "CumulativeVarianceExplained": 0.4377106421,
    "Method": "tCompCor",
    "Retained": true,
    "SingularValue": 172.2952614774,
    "VarianceExplained": 0.0772249506
  },
  "t_comp_cor_04": {
    "CumulativeVarianceExplained": 0.4938200079,
    "Method": "tCompCor",
    "Retained": true,
    "SingularValue": 146.8629318645,
    "VarianceExplained": 0.0561093658
  },
  "t_comp_cor_05": {
    "CumulativeVarianceExplained": 0.5413673895,
    "Method": "tCompCor",
    "Retained": true,
    "SingularValue": 135.1941241559,
    "VarianceExplained": 0.0475473816
  },
  "trans_x": {
    "Description": "Translation along left-right axis.",
    "Units": "mm"
  },
  "trans_y": {
    "Description": "Translation along anterior-posterior axis.",
    "Units": "mm"
  },
  "trans_z": {
    "Description": "Translation along superior-inferior axis.",
    "Units": "mm"
  },
  "w_comp_cor_00": {
    "CumulativeVarianceExplained": 0.0240036812,
    "Mask": "WM",
    "Method": "aCompCor",
    "Retained": true,
    "SingularValue": 113.8744426108,
    "VarianceExplained": 0.0240036812
  },
  "w_comp_cor_01": {
    "CumulativeVarianceExplained": 0.042538351,
    "Mask": "WM",
    "Method": "aCompCor",
    "Retained": true,
    "SingularValue": 100.064439218,
    "VarianceExplained": 0.0185346698
  },
  "w_comp_cor_02": {
    "CumulativeVarianceExplained": 0.0577504449,
    "Mask": "WM",
    "Method": "aCompCor",
    "Retained": true,
    "SingularValue": 90.6529283366,
    "VarianceExplained": 0.0152120939
  },
  "w_comp_cor_03": {
    "CumulativeVarianceExplained": 0.0711493643,
    "Mask": "WM",
    "Method": "aCompCor",
    "Retained": true,
    "SingularValue": 85.0789704445,
    "VarianceExplained": 0.0133989194
  },
  "w_comp_cor_04": {
    "CumulativeVarianceExplained": 0.084091419,
    "Mask": "WM",
    "Method": "aCompCor",
    "Retained": true,
    "SingularValue": 83.6159165992,
    "VarianceExplained": 0.0129420547
  },
  "w_comp_cor_05": {
    "CumulativeVarianceExplained": 0.0954152836,
    "Mask": "WM",
    "Method": "aCompCor",
    "Retained": true,
    "SingularValue": 78.2140317688,
    "VarianceExplained": 0.0113238646
  },
  "w_comp_cor_06": {
    "CumulativeVarianceExplained": 0.1063434841,
    "Mask": "WM",
    "Method": "aCompCor",
    "Retained": true,
    "SingularValue": 76.8354547382,
    "VarianceExplained": 0.0109282005
  },
  "w_comp_cor_07": {
    "CumulativeVarianceExplained": 0.1159529158,
    "Mask": "WM",
    "Method": "aCompCor",
    "Retained": true,
    "SingularValue": 72.0503661297,
    "VarianceExplained": 0.0096094317
  },
  "w_comp_cor_08": {
    "CumulativeVarianceExplained": 0.1251526337,
    "Mask": "WM",
    "Method": "aCompCor",
    "Retained": true,
    "SingularValue": 70.4976424978,
    "VarianceExplained": 0.0091997179
  },
  "w_comp_cor_09": {
    "CumulativeVarianceExplained": 0.1336912564,
    "Mask": "WM",
    "Method": "aCompCor",
    "Retained": true,
    "SingularValue": 67.91743119,
    "VarianceExplained": 0.0085386227
  },
  "w_comp_cor_10": {
    "CumulativeVarianceExplained": 0.1420741255,
    "Mask": "WM",
    "Method": "aCompCor",
    "Retained": true,
    "SingularValue": 67.2951369776,
    "VarianceExplained": 0.0083828691
  },
  "w_comp_cor_11": {
    "CumulativeVarianceExplained": 0.1499991784,
    "Mask": "WM",
    "Method": "aCompCor",
    "Retained": true,
    "SingularValue": 65.4317331727,
    "VarianceExplained": 0.0079250529
  },
  "w_comp_cor_12": {
    "CumulativeVarianceExplained": 0.1575960266,
    "Mask": "WM",
    "Method": "aCompCor",
    "Retained": true,
    "SingularValue": 64.0625266228,
    "VarianceExplained": 0.0075968482
  },
  "w_comp_cor_13": {
    "CumulativeVarianceExplained": 0.1650327292,
    "Mask": "WM",
    "Method": "aCompCor",
    "Retained": true,
    "SingularValue": 63.3836937728,
    "VarianceExplained": 0.0074367026
  },
  "w_comp_cor_14": {
    "CumulativeVarianceExplained": 0.1721814922,
    "Mask": "WM",
    "Method": "aCompCor",
    "Retained": true,
    "SingularValue": 62.1445128909,
    "VarianceExplained": 0.007148763
  },
  "w_comp_cor_15": {
    "CumulativeVarianceExplained": 0.1792842798,
    "Mask": "WM",
    "Method": "aCompCor",
    "Retained": true,
    "SingularValue": 61.9443579217,
    "VarianceExplained": 0.0071027877
  },
  "w_comp_cor_16": {
    "CumulativeVarianceExplained": 0.1863084004,
    "Mask": "WM",
    "Method": "aCompCor",
    "Retained": true,
    "SingularValue": 61.6003693724,
    "VarianceExplained": 0.0070241205
  },
  "w_comp_cor_17": {
    "CumulativeVarianceExplained": 0.1931326073,
    "Mask": "WM",
    "Method": "aCompCor",
    "Retained": true,
    "SingularValue": 60.7174371519,
    "VarianceExplained": 0.0068242069
  },
  "w_comp_cor_18": {
    "CumulativeVarianceExplained": 0.1997740583,
    "Mask": "WM",
    "Method": "aCompCor",
    "Retained": true,
    "SingularValue": 59.8988974011,
    "VarianceExplained": 0.0066414511
  },
  "w_comp_cor_19": {
    "CumulativeVarianceExplained": 0.2062682234,
    "Mask": "WM",
    "Method": "aCompCor",
    "Retained": true,
    "SingularValue": 59.2309912155,
    "VarianceExplained": 0.0064941651
  },
  "w_comp_cor_20": {
    "CumulativeVarianceExplained": 0.2126978898,
    "Mask": "WM",
    "Method": "aCompCor",
    "Retained": true,
    "SingularValue": 58.9361223185,
    "VarianceExplained": 0.0064296664
  },
  "w_comp_cor_21": {
    "CumulativeVarianceExplained": 0.2190431339,
    "Mask": "WM",
    "Method": "aCompCor",
    "Retained": true,
    "SingularValue": 58.5479247516,
    "VarianceExplained": 0.0063452441
  },
  "w_comp_cor_22": {
    "CumulativeVarianceExplained": 0.225332893,
    "Mask": "WM",
    "Method": "aCompCor",
    "Retained": true,
    "SingularValue": 58.2913813929,
    "VarianceExplained": 0.0062897592
  },
  "w_comp_cor_23": {
    "CumulativeVarianceExplained": 0.2315871741,
    "Mask": "WM",
    "Method": "aCompCor",
    "Retained": true,
    "SingularValue": 58.126749319,
    "VarianceExplained": 0.0062542811
  },
  "w_comp_cor_24": {
    "CumulativeVarianceExplained": 0.2377683725,
    "Mask": "WM",
    "Method": "aCompCor",
    "Retained": true,
    "SingularValue": 57.7861394126,
    "VarianceExplained": 0.0061811984
  },
  "w_comp_cor_25": {
    "CumulativeVarianceExplained": 0.2439213221,
    "Mask": "WM",
    "Method": "aCompCor",
    "Retained": true,
    "SingularValue": 57.6539434359,
    "VarianceExplained": 0.0061529496
  },
  "w_comp_cor_26": {
    "CumulativeVarianceExplained": 0.2500153948,
    "Mask": "WM",
    "Method": "aCompCor",
    "Retained": true,
    "SingularValue": 57.3774385027,
    "VarianceExplained": 0.0060940727
  },
  "w_comp_cor_27": {
    "CumulativeVarianceExplained": 0.2560466099,
    "Mask": "WM",
    "Method": "aCompCor",
    "Retained": true,
    "SingularValue": 57.0807600878,
    "VarianceExplained": 0.0060312151
  },
  "w_comp_cor_28": {
    "CumulativeVarianceExplained": 0.2620094447,
    "Mask": "WM",
    "Method": "aCompCor",
    "Retained": true,
    "SingularValue": 56.7562545151,
    "VarianceExplained": 0.0059628348
  },
  "w_comp_cor_29": {
    "CumulativeVarianceExplained": 0.2679366597,
    "Mask": "WM",
    "Method": "aCompCor",
    "Retained": true,
    "SingularValue": 56.5864798629,
    "VarianceExplained": 0.005927215
  },
  "w_comp_cor_30": {
    "CumulativeVarianceExplained": 0.2738033741,
    "Mask": "WM",
    "Method": "aCompCor",
    "Retained": true,
    "SingularValue": 56.2969431428,
    "VarianceExplained": 0.0058667144
  },
  "w_comp_cor_31": {
    "CumulativeVarianceExplained": 0.2796132695,
    "Mask": "WM",
    "Method": "aCompCor",
    "Retained": true,
    "SingularValue": 56.0236619997,
    "VarianceExplained": 0.0058098953
  },
  "w_comp_cor_32": {
    "CumulativeVarianceExplained": 0.2853947085,
    "Mask": "WM",
    "Method": "aCompCor",
    "Retained": true,
    "SingularValue": 55.8862943173,
    "VarianceExplained": 0.005781439
  },
  "w_comp_cor_33": {
    "CumulativeVarianceExplained": 0.2911279576,
    "Mask": "WM",
    "Method": "aCompCor",
    "Retained": true,
    "SingularValue": 55.6528930309,
    "VarianceExplained": 0.0057332491
  },
  "w_comp_cor_34": {
    "CumulativeVarianceExplained": 0.296826983,
    "Mask": "WM",
    "Method": "aCompCor",
    "Retained": true,
    "SingularValue": 55.4865390512,
    "VarianceExplained": 0.0056990254
  },
  "w_comp_cor_35": {
    "CumulativeVarianceExplained": 0.3024670552,
    "Mask": "WM",
    "Method": "aCompCor",
    "Retained": true,
    "SingularValue": 55.1988043038,
    "VarianceExplained": 0.0056400722
  },
  "w_comp_cor_36": {
    "CumulativeVarianceExplained": 0.3080976334,
    "Mask": "WM",
    "Method": "aCompCor",
    "Retained": true,
    "SingularValue": 55.1523263347,
    "VarianceExplained": 0.0056305782
  },
  "w_comp_cor_37": {
    "CumulativeVarianceExplained": 0.3136618474,
    "Mask": "WM",
    "Method": "aCompCor",
    "Retained": true,
    "SingularValue": 54.8263396621,
    "VarianceExplained": 0.005564214
  },
  "w_comp_cor_38": {
    "CumulativeVarianceExplained": 0.3192090225,
    "Mask": "WM",
    "Method": "aCompCor",
    "Retained": true,
    "SingularValue": 54.74232984,
    "VarianceExplained": 0.0055471751
  },
  "w_comp_cor_39": {
    "CumulativeVarianceExplained": 0.3247124236,
    "Mask": "WM",
    "Method": "aCompCor",
    "Retained": true,
    "SingularValue": 54.5259100231,
    "VarianceExplained": 0.0055034011
  },
  "w_comp_cor_40": {
    "CumulativeVarianceExplained": 0.3301866862,
    "Mask": "WM",
    "Method": "aCompCor",
    "Retained": true,
    "SingularValue": 54.3813705973,
    "VarianceExplained": 0.0054742625
  },
  "w_comp_cor_41": {
    "CumulativeVarianceExplained": 0.335617223,
    "Mask": "WM",
    "Method": "aCompCor",
    "Retained": true,
    "SingularValue": 54.1637496503,
    "VarianceExplained": 0.0054305369
  },
  "w_comp_cor_42": {
    "CumulativeVarianceExplained": 0.3410402147,
    "Mask": "WM",
    "Method": "aCompCor",
    "Retained": true,
    "SingularValue": 54.126109038,
    "VarianceExplained": 0.0054229917
  },
  "w_comp_cor_43": {
    "CumulativeVarianceExplained": 0.3464070521,
    "Mask": "WM",
    "Method": "aCompCor",
    "Retained": true,
    "SingularValue": 53.8451458549,
    "VarianceExplained": 0.0053668374
  },
  "w_comp_cor_44": {
    "CumulativeVarianceExplained": 0.3517429321,
    "Mask": "WM",
    "Method": "aCompCor",
    "Retained": true,
    "SingularValue": 53.6896244727,
    "VarianceExplained": 0.00533588
  },
  "w_comp_cor_45": {
    "CumulativeVarianceExplained": 0.3570762253,
    "Mask": "WM",
    "Method": "aCompCor",
    "Retained": true,
    "SingularValue": 53.6766086349,
    "VarianceExplained": 0.0053332932
  },
  "w_comp_cor_46": {
    "CumulativeVarianceExplained": 0.3623540486,
    "Mask": "WM",
    "Method": "aCompCor",
    "Retained": true,
    "SingularValue": 53.3967424001,
    "VarianceExplained": 0.0052778233
  },
  "w_comp_cor_47": {
    "CumulativeVarianceExplained": 0.3676083401,
    "Mask": "WM",
    "Method": "aCompCor",
    "Retained": true,
    "SingularValue": 53.2775713525,
    "VarianceExplained": 0.0052542915
  },
  "w_comp_cor_48": {
    "CumulativeVarianceExplained": 0.3728485931,
    "Mask": "WM",
    "Method": "aCompCor",
    "Retained": true,
    "SingularValue": 53.2063502216,
    "VarianceExplained": 0.005240253
  },
  "w_comp_cor_49": {
    "CumulativeVarianceExplained": 0.3780503539,
    "Mask": "WM",
    "Method": "aCompCor",
    "Retained": true,
    "SingularValue": 53.0105762043,
    "VarianceExplained": 0.0052017607
  },
  "w_comp_cor_50": {
    "CumulativeVarianceExplained": 0.3832373068,
    "Mask": "WM",
    "Method": "aCompCor",
    "Retained": true,
    "SingularValue": 52.9350703153,
    "VarianceExplained": 0.005186953
  },
  "w_comp_cor_51": {
    "CumulativeVarianceExplained": 0.3883748396,
    "Mask": "WM",
    "Method": "aCompCor",
    "Retained": true,
    "SingularValue": 52.6822896504,
    "VarianceExplained": 0.0051375328
  },
  "w_comp_cor_52": {
    "CumulativeVarianceExplained": 0.3934793938,
    "Mask": "WM",
    "Method": "aCompCor",
    "Retained": true,
    "SingularValue": 52.512929852,
    "VarianceExplained": 0.0051045542
  },
  "w_comp_cor_53": {
    "CumulativeVarianceExplained": 0.3985334672,
    "Mask": "WM",
    "Method": "aCompCor",
    "Retained": true,
    "SingularValue": 52.2526250038,
    "VarianceExplained": 0.0050540734
  },
  "w_comp_cor_54": {
    "CumulativeVarianceExplained": 0.4035664106,
    "Mask": "WM",
    "Method": "aCompCor",
    "Retained": true,
    "SingularValue": 52.1432818842,
    "VarianceExplained": 0.0050329434
  },
  "w_comp_cor_55": {
    "CumulativeVarianceExplained": 0.4085654323,
    "Mask": "WM",
    "Method": "aCompCor",
    "Retained": true,
    "SingularValue": 51.9672636365,
    "VarianceExplained": 0.0049990217
  },
  "w_comp_cor_56": {
    "CumulativeVarianceExplained": 0.4135550023,
    "Mask": "WM",
    "Method": "aCompCor",
    "Retained": true,
    "SingularValue": 51.9181128271,
    "VarianceExplained": 0.00498957
  },
  "w_comp_cor_57": {
    "CumulativeVarianceExplained": 0.4185294433,
    "Mask": "WM",
    "Method": "aCompCor",
    "Retained": true,
    "SingularValue": 51.8393422249,
    "VarianceExplained": 0.004974441
  },
  "w_comp_cor_58": {
    "CumulativeVarianceExplained": 0.4234585417,
    "Mask": "WM",
    "Method": "aCompCor",
    "Retained": true,
    "SingularValue": 51.6025404245,
    "VarianceExplained": 0.0049290984
  },
  "w_comp_cor_59": {
    "CumulativeVarianceExplained": 0.4283722979,
    "Mask": "WM",
    "Method": "aCompCor",
    "Retained": true,
    "SingularValue": 51.5221693231,
    "VarianceExplained": 0.0049137562
  },
  "w_comp_cor_60": {
    "CumulativeVarianceExplained": 0.4332632755,
    "Mask": "WM",
    "Method": "aCompCor",
    "Retained": true,
    "SingularValue": 51.4026105516,
    "VarianceExplained": 0.0048909776
  },
  "w_comp_cor_61": {
    "CumulativeVarianceExplained": 0.438125967,
    "Mask": "WM",
    "Method": "aCompCor",
    "Retained": true,
    "SingularValue": 51.2537560176,
    "VarianceExplained": 0.0048626915
  },
  "w_comp_cor_62": {
    "CumulativeVarianceExplained": 0.442945065,
    "Mask": "WM",
    "Method": "aCompCor",
    "Retained": true,
    "SingularValue": 51.0234967803,
    "VarianceExplained": 0.004819098
  },
  "w_comp_cor_63": {
    "CumulativeVarianceExplained": 0.4477563118,
    "Mask": "WM",
    "Method": "aCompCor",
    "Retained": true,
    "SingularValue": 50.9819165951,
    "VarianceExplained": 0.0048112468
  },
  "w_comp_cor_64": {
    "CumulativeVarianceExplained": 0.4525506752,
    "Mask": "WM",
    "Method": "aCompCor",
    "Retained": true,
    "SingularValue": 50.8923858358,
    "VarianceExplained": 0.0047943633
  },
  "w_comp_cor_65": {
    "CumulativeVarianceExplained": 0.4573142333,
    "Mask": "WM",
    "Method": "aCompCor",
    "Retained": true,
    "SingularValue": 50.7286229113,
    "VarianceExplained": 0.0047635581
  },
  "w_comp_cor_66": {
    "CumulativeVarianceExplained": 0.4620650803,
    "Mask": "WM",
    "Method": "aCompCor",
    "Retained": true,
    "SingularValue": 50.6608954933,
    "VarianceExplained": 0.004750847
  },
  "w_comp_cor_67": {
    "CumulativeVarianceExplained": 0.4667844202,
    "Mask": "WM",
    "Method": "aCompCor",
    "Retained": true,
    "SingularValue": 50.4926272395,
    "VarianceExplained": 0.0047193399
  },
  "w_comp_cor_68": {
    "CumulativeVarianceExplained": 0.4714877839,
    "Mask": "WM",
    "Method": "aCompCor",
    "Retained": true,
    "SingularValue": 50.407089036,
    "VarianceExplained": 0.0047033636
  },
  "w_comp_cor_69": {
    "CumulativeVarianceExplained": 0.4761573088,
    "Mask": "WM",
    "Method": "aCompCor",
    "Retained": true,
    "SingularValue": 50.2254326678,
    "VarianceExplained": 0.0046695249
  },
  "w_comp_cor_70": {
    "CumulativeVarianceExplained": 0.4808073475,
    "Mask": "WM",
    "Method": "aCompCor",
    "Retained": true,
    "SingularValue": 50.1205267624,
    "VarianceExplained": 0.0046500388
  },
  "w_comp_cor_71": {
    "CumulativeVarianceExplained": 0.4854381618,
    "Mask": "WM",
    "Method": "aCompCor",
    "Retained": true,
    "SingularValue": 50.0168134239,
    "VarianceExplained": 0.0046308142
  },
  "w_comp_cor_72": {
    "CumulativeVarianceExplained": 0.4900539553,
    "Mask": "WM",
    "Method": "aCompCor",
    "Retained": true,
    "SingularValue": 49.9356292425,
    "VarianceExplained": 0.0046157935
  },
  "w_comp_cor_73": {
    "CumulativeVarianceExplained": 0.4946140926,
    "Mask": "WM",
    "Method": "aCompCor",
    "Retained": true,
    "SingularValue": 49.6336596943,
    "VarianceExplained": 0.0045601373
  },
  "w_comp_cor_74": {
    "CumulativeVarianceExplained": 0.4991504065,
    "Mask": "WM",
    "Method": "aCompCor",
    "Retained": true,
    "SingularValue": 49.503839969,
    "VarianceExplained": 0.0045363139
  },
  "w_comp_cor_75": {
    "CumulativeVarianceExplained": 0.5036673955,
    "Mask": "WM",
    "Method": "aCompCor",
    "Retained": true,
    "SingularValue": 49.3982828655,
    "VarianceExplained": 0.0045169889
  }
}